Workbook
Name Discipline: '[1]Discipline Codes'!$A$5:$A$21
Name Discipline: 'Discipline Codes'!$A$5:$A$23
Name DISCPPE: '[1]Discipline Codes'!$D$5:$D$14
Name DISCPPE: 'Discipline Codes'!#REF!
Name Month: [1]Dropdown!$A$2:$A$13
Name Month: #REF!
Name mylist: #REF!
Name Patterns: '[2]List Fields'!$B$2:$B$108
Name Patterns: #REF!
Name Phase: [1]Dropdown!$D$2:$D$6
Name Phase: #REF!
Name PNO: [1]Dropdown!$F$2:$F$4
Name PNO: #REF!
Name PPE: [1]Dropdown!$B$2:$B$3
Name PPE: #REF!
Name Project: [1]Dropdown!$E$2:$E$3
Name Project: #REF!
Name Quote: [1]Dropdown!$C$2:$C$3
Name Quote: #REF!
Name Rev: [1]Revision!$H$2:$H$12
Name Rev: #REF!
Name Type: '[1]Document and Drawing Type'!$A$8:$A$118
Name Type: 'Document and Drawing Type'!$A$5:$A$29
Name WBS: 'PPE WBS Codes'!$E$2:$E$31
Name WBS: #REF!
Name WBSD: 'PPE WBS Codes'!$F$2:$F$31
Name WBSD: #REF!

Sheet Tracker
A1: Area/ WBS No. | B1: Discipline | C1: RDMC Document Number | D1: Sum of % Complete
A2: 6200 | D2: 0
A3: 6240 | D3: 0
A4: 6243 | D4: 0
A5: 6250 | D5: 0
A6: 6260 | D6: 0
A7: 6262 | D7: 0
A8: 6263 | D8: 0
A9: 6264 | D9: 0
A10: 6280 | D10: 0
A11: 6286 | D11: 0
A12: 6292 | D12: 0
A13: 0000 | D13: 0
A14: 0100 | D14: 0
A15: Grand Total | D15: 0

Sheet Docs not in Use
A1: Project Number | B1: Package Number | C1: Area/ WBS No. | D1: Discipline | E1: Document Type | F1: Sequential Number | G1: Revision | H1: RDMC Document Number | I1: PPE Doc Number | J1: Sht. # of # | K1: Area / Facility | L1: Major Description | M1: Broad Type | N1: Full Title | O1: Rev A Transmittal Date | P1: Rev 0 Transmittal Date | Q1: Aconex Doc Status | R1: Aconex Review Status | S1: % Complete | T1: Doc Owner | U1: Comments | V1: Due Date | W1: Main Group | X1: Sub Group | Y1: BH | Z1: Drawing Pack
A2: 6105A | B2: K124 | C2: 0000 | D2: B | E2: REQ | F2: 0001 | G2: A | H2: =A2&B2&"-"&C2&"-"&D2&E2&"-"&F2 -> 6105AK124-0000-BREQ-0001 | I2: ="Q24050972"&"-"&"09"&"-"&C2&"-"&D2&"-"&E2&"-"&F2 -> Q24050972-09-0000-B-REQ-0001 | K2: General | L2: Change Order Request | M2: General | N2: =K2&" - "&L2&" - "&M2 -> General - Change Order Request - General | Q2: No status | R2: No status | T2: MK | U2: COR'S | W2: N/A | X2: N/A | Y2: N/A | Z2: N/A
A3: 6105A | B3: K124 | C3: 0000 | D3: G | E3: PRC | F3: 0001 | G3: A | H3: =A3&B3&"-"&C3&"-"&D3&E3&"-"&F3 -> 6105AK124-0000-GPRC-0001 | I3: ="Q24050972"&"-"&"09"&"-"&C3&"-"&D3&"-"&E3&"-"&F3 -> Q24050972-09-0000-G-PRC-0001 | K3: General | L3: PPE Commissioning SharePoint Document Transmittal Procedure | M3: General | N3: =K3&" - "&L3&" - "&M3 -> General - PPE Commissioning SharePoint Document Transmittal Procedure - General | Q3: No status | R3: No status | T3: CP | W3: N/A | X3: N/A | Y3: N/A | Z3: N/A
A4: 6105A | B4: K124 | C4: 0000 | D4: G | E4: PRC | F4: 0002 | G4: A | H4: =A4&B4&"-"&C4&"-"&D4&E4&"-"&F4 -> 6105AK124-0000-GPRC-0002 | I4: ="Q24050972"&"-"&"09"&"-"&C4&"-"&D4&"-"&E4&"-"&F4 -> Q24050972-09-0000-G-PRC-0002 | K4: General | L4: Internal Document Review Procedure | M4: General | N4: =K4&" - "&L4&" - "&M4 -> General - Internal Document Review Procedure - General | Q4: No status | R4: No status | T4: CP | W4: N/A | X4: N/A | Y4: N/A | Z4: N/A
A5: 6105A | B5: K124 | C5: 0000 | D5: G | E5: PRC | F5: 0003 | G5: A | H5: =A5&B5&"-"&C5&"-"&D5&E5&"-"&F5 -> 6105AK124-0000-GPRC-0003 | I5: ="Q24050972"&"-"&"10"&"-"&C5&"-"&D5&"-"&E5&"-"&F5 -> Q24050972-10-0000-G-PRC-0003 | K5: General | L5: PPE Vendor SharePoint Procedure | M5: General | N5: =K5&" - "&L5&" - "&M5 -> General - PPE Vendor SharePoint Procedure - General | Q5: No status | R5: No status | T5: CP | W5: N/A | X5: N/A | Y5: N/A | Z5: N/A
A6: 6105A | B6: K124 | C6: 0000 | D6: G | E6: PRC | F6: 0004 | G6: A | H6: =A6&B6&"-"&C6&"-"&D6&E6&"-"&F6 -> 6105AK124-0000-GPRC-0004 | I6: ="Q24050972"&"-"&"01"&"-"&C6&"-"&D6&"-"&E6&"-"&F6 -> Q24050972-01-0000-G-PRC-0004 | K6: General | L6: PPE Formal App Review Procedure | M6: General | N6: =K6&" - "&L6&" - "&M6 -> General - PPE Formal App Review Procedure - General | Q6: No status | R6: No status | T6: CP | W6: N/A | X6: N/A | Y6: N/A | Z6: N/A

Sheet CDDL
A1: Project Number | B1: Package Number | C1: Area/ WBS No. | D1: Discipline | E1: Document Type | F1: Sequential Number | G1: Revision | H1: RDMC Document Number | I1: PPE Doc Number | J1: Sht. # of # | K1: Area / Facility | L1: Major Description | M1: Broad Type | N1: Full Title | O1: Rev A Transmittal Date | P1: Rev 0 Transmittal Date | Q1: Aconex Doc Status | R1: Aconex Review Status | S1: % Complete | T1: Doc Owner | U1: Comments | V1: Due Date | W1: Main Group | X1: Sub Group | Y1: BH | Z1: Drawing Pack | AA1: Activity ID | AB1: Schedule Status
A2: 6105A | B2: K124 | C2: 6200 | D2: E | E2: BOM | F2: 0001 | G2: A | H2: =A2&B2&"-"&C2&"-"&D2&E2&"-"&F2 -> 6105AK124-6200-EBOM-0001 | I2: ="Q24050972"&"-"&"07"&"-"&C2&"-"&D2&"-"&E2&"-"&F2 -> Q24050972-07-6200-E-BOM-0001 | K2: =VLOOKUP(C2,'PPE WBS Codes'!$E$3:$F$79,2,0) -> On-Site Power Supply and Transmission | L2: Neutral Earthing Compensator Resistor (33kV NECr) | M2: Bill of Material | N2: =K2&" - "&L2&" - "&M2 -> On-Site Power Supply and Transmission - Neutral Earthing Compensator Resistor (33kV NECr) - Bill of Material | Q2: =IFERROR(VLOOKUP(PPE_PH1_CDDL[[#This Row],[RDMC Document Number]],[3]Docs!$B:$F,4,0),"No Placeholder Yet") -> RES - Reserved Placeholder | R2: =IFERROR(VLOOKUP(PPE_PH1_CDDL[[#This Row],[RDMC Document Number]],[3]Docs!$B:$F,5,0),"No Placeholder Yet") -> Pending | S2: =IF(AND(O2<>"",P2<>"",R2="Approved"),100%, IF(AND(O2<>"",P2<>""),66.67%, IF(O2<>"",33.33%, 0))) -> 0 | T2: IS | V2: TENDER | W2: Neutral Earthing Compensator Resistor (33kV NECr) | X2: Bill of Material | AB2: Pending
A3: 6105A | B3: K124 | C3: 6200 | D3: E | E3: BOM | F3: 0002 | G3: A | H3: =A3&B3&"-"&C3&"-"&D3&E3&"-"&F3 -> 6105AK124-6200-EBOM-0002 | I3: ="Q24050972"&"-"&"07"&"-"&C3&"-"&D3&"-"&E3&"-"&F3 -> Q24050972-07-6200-E-BOM-0002 | K3: =VLOOKUP(C3,'PPE WBS Codes'!$E$3:$F$79,2,0) -> On-Site Power Supply and Transmission | L3: Neutral Earthing Reactor (11kV NER) | M3: Bill of Material | N3: =K3&" - "&L3&" - "&M3 -> On-Site Power Supply and Transmission - Neutral Earthing Reactor (11kV NER) - Bill of Material | Q3: =IFERROR(VLOOKUP(PPE_PH1_CDDL[[#This Row],[RDMC Document Number]],[3]Docs!$B:$F,4,0),"No Placeholder Yet") -> RES - Reserved Placeholder | R3: =IFERROR(VLOOKUP(PPE_PH1_CDDL[[#This Row],[RDMC Document Number]],[3]Docs!$B:$F,5,0),"No Placeholder Yet") -> Pending | S3: =IF(AND(O3<>"",P3<>"",R3="Approved"),100%, IF(AND(O3<>"",P3<>""),66.67%, IF(O3<>"",33.33%, 0))) -> 0 | T3: IS | V3: TENDER | W3: Neutral Earthing Reactor (11kV NER) | X3: Bill of Material | AB3: Pending
A4: 6105A | B4: K124 | C4: 6200 | D4: E | E4: BOM | F4: 0003 | G4: A | H4: =A4&B4&"-"&C4&"-"&D4&E4&"-"&F4 -> 6105AK124-6200-EBOM-0003 | I4: ="Q24050972"&"-"&"07"&"-"&C4&"-"&D4&"-"&E4&"-"&F4 -> Q24050972-07-6200-E-BOM-0003 | K4: =VLOOKUP(C4,'PPE WBS Codes'!$E$3:$F$79,2,0) -> On-Site Power Supply and Transmission | L4: Power Transformers - 33/11kV - 25MVA | M4: Bill of Material | N4: =K4&" - "&L4&" - "&M4 -> On-Site Power Supply and Transmission - Power Transformers - 33/11kV - 25MVA - Bill of Material | Q4: =IFERROR(VLOOKUP(PPE_PH1_CDDL[[#This Row],[RDMC Document Number]],[3]Docs!$B:$F,4,0),"No Placeholder Yet") -> RES - Reserved Placeholder | R4: =IFERROR(VLOOKUP(PPE_PH1_CDDL[[#This Row],[RDMC Document Number]],[3]Docs!$B:$F,5,0),"No Placeholder Yet") -> Pending | S4: =IF(AND(O4<>"",P4<>"",R4="Approved"),100%, IF(AND(O4<>"",P4<>""),66.67%, IF(O4<>"",33.33%, 0))) -> 0 | T4: IS | V4: TENDER | W4: Power Transformers | X4: Bill of Material | AB4: Pending
A5: 6105A | B5: K124 | C5: 6263 | D5: E | E5: BOM | F5: 0001 | G5: A | H5: =A5&B5&"-"&C5&"-"&D5&E5&"-"&F5 -> 6105AK124-6263-EBOM-0001 | I5: ="Q24050972"&"-"&"07"&"-"&C5&"-"&D5&"-"&E5&"-"&F5 -> Q24050972-07-6263-E-BOM-0001 | K5: =VLOOKUP(C5,'PPE WBS Codes'!$E$3:$F$79,2,0) -> 36 MVA Power Station 1 | L5: High Speed Diesel Generators | M5: Bill of Material | N5: =K5&" - "&L5&" - "&M5 -> 36 MVA Power Station 1 - High Speed Diesel Generators - Bill of Material | Q5: =IFERROR(VLOOKUP(PPE_PH1_CDDL[[#This Row],[RDMC Document Number]],[3]Docs!$B:$F,4,0),"No Placeholder Yet") -> RES - Reserved Placeholder | R5: =IFERROR(VLOOKUP(PPE_PH1_CDDL[[#This Row],[RDMC Document Number]],[3]Docs!$B:$F,5,0),"No Placeholder Yet") -> Pending | S5: =IF(AND(O5<>"",P5<>"",R5="Approved"),100%, IF(AND(O5<>"",P5<>""),66.67%, IF(O5<>"",33.33%, 0))) -> 0 | T5: IS | V5: TENDER | W5: High Speed Diesel Generators | X5: Bill of Material | AB5: Pending
A6: 6105A | B6: K124 | C6: 6262 | D6: E | E6: BOM | F6: 0001 | G6: A | H6: =A6&B6&"-"&C6&"-"&D6&E6&"-"&F6 -> 6105AK124-6262-EBOM-0001 | I6: ="Q24050972"&"-"&"11"&"-"&C6&"-"&D6&"-"&E6&"-"&F6 -> Q24050972-11-6262-E-BOM-0001 | J6: Sht 1 of 1 | K6: =VLOOKUP(C6,'PPE WBS Codes'!$E$3:$F$79,2,0) -> Emergency Power Substation 1 and Control Room 1 | L6: 33/11kV Substation | M6: Yard Plant & Equipment - Bill of Material | N6: =K6&" - "&L6&" - "&M6&" - "&J6 -> Emergency Power Substation 1 and Control Room 1 - 33/11kV Substation - Yard Plant & Equipment - Bill of Material - Sht 1 of 1 | Q6: =IFERROR(VLOOKUP(PPE_PH1_CDDL[[#This Row],[RDMC Document Number]],[3]Docs!$B:$F,4,0),"No Placeholder Yet") -> RES - Reserved Placeholder | R6: =IFERROR(VLOOKUP(PPE_PH1_CDDL[[#This Row],[RDMC Document Number]],[3]Docs!$B:$F,5,0),"No Placeholder Yet") -> Pending | S6: =IF(AND(O6<>"",P6<>"",R6="Approved"),100%, IF(AND(O6<>"",P6<>""),66.67%, IF(O6<>"",33.33%, 0))) -> 0 | T6: IS | V6: 46157 | W6: 33/11kV Substation | X6: Bill of Material | AB6: Pending
A7: 6105A | B7: K124 | C7: 6200 | D7: B | E7: BOS | F7: 0001 | G7: A | H7: =A7&B7&"-"&C7&"-"&D7&E7&"-"&F7 -> 6105AK124-6200-BBOS-0001 | I7: ="Q24050972"&"-"&"07"&"-"&C7&"-"&D7&"-"&E7&"-"&F7 -> Q24050972-07-6200-B-BOS-0001 | K7: =VLOOKUP(C7,'PPE WBS Codes'!$E$3:$F$79,2,0) -> On-Site Power Supply and Transmission | L7: PPE EP & CM Contractual Schedule | M7: Basis of Schedule | N7: =K7&" - "&L7&" - "&M7 -> On-Site Power Supply and Transmission - PPE EP & CM Contractual Schedule - Basis of Schedule | Q7: =IFERROR(VLOOKUP(PPE_PH1_CDDL[[#This Row],[RDMC Document Number]],[3]Docs!$B:$F,4,0),"No Placeholder Yet") -> RES - Reserved Placeholder | R7: =IFERROR(VLOOKUP(PPE_PH1_CDDL[[#This Row],[RDMC Document Number]],[3]Docs!$B:$F,5,0),"No Placeholder Yet") -> Pending | S7: =IF(AND(O7<>"",P7<>"",R7="Approved"),100%, IF(AND(O7<>"",P7<>""),66.67%, IF(O7<>"",33.33%, 0))) -> 0 | T7: FO | V7: TENDER | W7: PPE EP & CM Contractual Schedule | X7: Basis of Schedule | AB7: Pending
A8: 6105A | B8: K124 | C8: 0100 | D8: G | E8: CHR | F8: 0001 | G8: A | H8: =A8&B8&"-"&C8&"-"&D8&E8&"-"&F8 -> 6105AK124-0100-GCHR-0001 | I8: ="Q24050972"&"-"&"01"&"-"&C8&"-"&D8&"-"&E8&"-"&F8 -> Q24050972-01-0100-G-CHR-0001 | K8: =VLOOKUP(C8,'PPE WBS Codes'!$E$3:$F$79,2,0) -> Project Site Wide | L8: Phase 1 Construction Management Organogram | M8: General | N8: =K8&" - "&L8&" - "&M8 -> Project Site Wide - Phase 1 Construction Management Organogram - General | Q8: =IFERROR(VLOOKUP(PPE_PH1_CDDL[[#This Row],[RDMC Document Number]],[3]Docs!$B:$F,4,0),"No Placeholder Yet") -> RES - Reserved Placeholder | R8: =IFERROR(VLOOKUP(PPE_PH1_CDDL[[#This Row],[RDMC Document Number]],[3]Docs!$B:$F,5,0),"No Placeholder Yet") -> Pending | S8: =IF(AND(O8<>"",P8<>"",R8="Approved"),100%, IF(AND(O8<>"",P8<>""),66.67%, IF(O8<>"",33.33%, 0))) -> 0 | T8: JM | V8: 46157 | W8: Organogram | X8: General | AB8: Pending
A9: 6105A | B9: K124 | C9: 6290 | D9: E | E9: DBD | F9: 0001 | G9: 0 | H9: =A9&B9&"-"&C9&"-"&D9&E9&"-"&F9 -> 6105AK124-6290-EDBD-0001 | I9: ="Q24050972"&"-"&"11"&"-"&C9&"-"&D9&"-"&E9&"-"&F9 -> Q24050972-11-6290-E-DBD-0001 | K9: =VLOOKUP(C9,'PPE WBS Codes'!$E$3:$F$79,2,0) -> Renewable Energy | L9: 150MW Solar PV Plant | M9: Basis of Design | N9: =K9&" - "&L9&" - "&M9 -> Renewable Energy - 150MW Solar PV Plant - Basis of Design | O9: 46093 | P9: 46157 | Q9: =IFERROR(VLOOKUP(PPE_PH1_CDDL[[#This Row],[RDMC Document Number]],[3]Docs!$B:$F,4,0),"No Placeholder Yet") -> IFU - Issued for Use | R9: =IFERROR(VLOOKUP(PPE_PH1_CDDL[[#This Row],[RDMC Document Number]],[3]Docs!$B:$F,5,0),"No Placeholder Yet") -> Pending | S9: =IF(AND(O9<>"",P9<>"",R9="Approved"),100%, IF(AND(O9<>"",P9<>""),66.67%, IF(O9<>"",33.33%, 0))) -> 0.6667 | T9: NL | W9: 150MW Solar PV Plant | X9: Basis of Design | AB9: Pending
A10: 6105A | B10: K124 | C10: 6290 | D10: E | E10: DBD | F10: 0002 | G10: 0 | H10: =A10&B10&"-"&C10&"-"&D10&E10&"-"&F10 -> 6105AK124-6290-EDBD-0002 | I10: ="Q24050972"&"-"&"11"&"-"&C10&"-"&D10&"-"&E10&"-"&F10 -> Q24050972-11-6290-E-DBD-0002 | K10: =VLOOKUP(C10,'PPE WBS Codes'!$E$3:$F$79,2,0) -> Renewable Energy | L10: 50MW BESS System | M10: Basis of Design | N10: =K10&" - "&L10&" - "&M10 -> Renewable Energy - 50MW BESS System - Basis of Design | O10: 46094 | P10: 46157 | Q10: =IFERROR(VLOOKUP(PPE_PH1_CDDL[[#This Row],[RDMC Document Number]],[3]Docs!$B:$F,4,0),"No Placeholder Yet") -> IFU - Issued for Use | R10: =IFERROR(VLOOKUP(PPE_PH1_CDDL[[#This Row],[RDMC Document Number]],[3]Docs!$B:$F,5,0),"No Placeholder Yet") -> Pending | S10: =IF(AND(O10<>"",P10<>"",R10="Approved"),100%, IF(AND(O10<>"",P10<>""),66.67%, IF(O10<>"",33.33%, 0))) -> 0.6667 | T10: NL | W10: 50MW BESS System | X10: Basis of Design | AB10: Pending
A11: 6105A | B11: K124 | C11: 0000 | D11: G | E11: DDR | F11: 0001 | G11: A | H11: =A11&B11&"-"&C11&"-"&D11&E11&"-"&F11 -> 6105AK124-0000-GDDR-0001 | I11: ="Q24050972"&"-"&"08"&"-"&C11&"-"&D11&"-"&E11&"-"&F11 -> Q24050972-08-0000-G-DDR-0001 | K11: General | L11: PPE Contractor Document and Data List (CDDL) | M11: CDDL | N11: =L11 -> PPE Contractor Document and Data List (CDDL) | Q11: =IFERROR(VLOOKUP(PPE_PH1_CDDL[[#This Row],[RDMC Document Number]],[3]Docs!$B:$F,4,0),"No Placeholder Yet") -> IFI - Issued for Information | R11: =IFERROR(VLOOKUP(PPE_PH1_CDDL[[#This Row],[RDMC Document Number]],[3]Docs!$B:$F,5,0),"No Placeholder Yet") -> Reviewed | S11: =IF(AND(O11<>"",P11<>"",R11="Approved"),100%, IF(AND(O11<>"",P11<>""),66.67%, IF(O11<>"",33.33%, 0))) -> 0 | T11: RV | W11: CDDL | X11: General | AB11: Pending
A12: 6105A | B12: K124 | C12: 6200 | D12: E | E12: DST | F12: 0001 | G12: A | H12: =A12&B12&"-"&C12&"-"&D12&E12&"-"&F12 -> 6105AK124-6200-EDST-0001 | I12: ="Q24050972"&"-"&"03"&"-"&C12&"-"&D12&"-"&E12&"-"&F12 -> Q24050972-03-6200-E-DST-0001 | K12: =VLOOKUP(C12,'PPE WBS Codes'!$E$3:$F$79,2,0) -> On-Site Power Supply and Transmission | L12: Primary Electrical Reticulation Network - Solar PV Switchyard, Boreholes and Camp | M12: Datasheet | N12: =K12&" - "&L12&" - "&M12 -> On-Site Power Supply and Transmission - Primary Electrical Reticulation Network - Solar PV Switchyard, Boreholes and Camp - Datasheet | Q12: =IFERROR(VLOOKUP(PPE_PH1_CDDL[[#This Row],[RDMC Document Number]],[3]Docs!$B:$F,4,0),"No Placeholder Yet") -> RES - Reserved Placeholder | R12: =IFERROR(VLOOKUP(PPE_PH1_CDDL[[#This Row],[RDMC Document Number]],[3]Docs!$B:$F,5,0),"No Placeholder Yet") -> Pending | S12: =IF(AND(O12<>"",P12<>"",R12="Approved"),100%, IF(AND(O12<>"",P12<>""),66.67%, IF(O12<>"",33.33%, 0))) -> 0 | T12: MM | V12: TENDER | W12: Primary Electrical Reticulation Network | X12: Solar PV Switchyard, Boreholes and Camp | AB12: Pending
A13: 6105A | B13: K124 | C13: 6200 | D13: E | E13: DST | F13: 0016 | G13: A | H13: =A13&B13&"-"&C13&"-"&D13&E13&"-"&F13 -> 6105AK124-6200-EDST-0016 | I13: ="Q24050972"&"-"&"07"&"-"&C13&"-"&D13&"-"&E13&"-"&F13 -> Q24050972-07-6200-E-DST-0016 | J13: Sht 1 of 1 | K13: =VLOOKUP(C13,'PPE WBS Codes'!$E$3:$F$79,2,0) -> On-Site Power Supply and Transmission | L13: Main Consumer Sub | M13: Layout | N13: =K13&" - "&L13&" - "&M13&" - "&J13 -> On-Site Power Supply and Transmission - Main Consumer Sub - Layout - Sht 1 of 1 | Q13: =IFERROR(VLOOKUP(PPE_PH1_CDDL[[#This Row],[RDMC Document Number]],[3]Docs!$B:$F,4,0),"No Placeholder Yet") -> RES - Reserved Placeholder | R13: =IFERROR(VLOOKUP(PPE_PH1_CDDL[[#This Row],[RDMC Document Number]],[3]Docs!$B:$F,5,0),"No Placeholder Yet") -> Pending | S13: =IF(AND(O13<>"",P13<>"",R13="Approved"),100%, IF(AND(O13<>"",P13<>""),66.67%, IF(O13<>"",33.33%, 0))) -> 0 | T13: CLR | V13: TENDER | W13: Main Consumer Sub | X13: Layout | AB13: Pending
A14: 6105A | B14: K124 | C14: 6243 | D14: E | E14: DST | F14: 0002 | G14: 0 | H14: =A14&B14&"-"&C14&"-"&D14&E14&"-"&F14 -> 6105AK124-6243-EDST-0002 | I14: ="Q24050972"&"-"&"06"&"-"&C14&"-"&D14&"-"&E14&"-"&F14 -> Q24050972-06-6243-E-DST-0002 | K14: =VLOOKUP(C14,'PPE WBS Codes'!$E$3:$F$79,2,0) -> 220/33 kV Plant Main Substation | L14: On-Site Power Supply & Transmission MV 33kV Main Consumer Plant Switchgear | M14: Datasheet | N14: =K14&" - "&L14&" - "&M14 -> 220/33 kV Plant Main Substation - On-Site Power Supply & Transmission MV 33kV Main Consumer Plant Switchgear - Datasheet | O14: 45957 | P14: 46093 | Q14: =IFERROR(VLOOKUP(PPE_PH1_CDDL[[#This Row],[RDMC Document Number]],[3]Docs!$B:$F,4,0),"No Placeholder Yet") -> IFU - Issued for Use | R14: =IFERROR(VLOOKUP(PPE_PH1_CDDL[[#This Row],[RDMC Document Number]],[3]Docs!$B:$F,5,0),"No Placeholder Yet") -> Rejected - Revise & Resubmit | S14: =IF(AND(O14<>"",P14<>"",R14="Approved"),100%, IF(AND(O14<>"",P14<>""),66.67%, IF(O14<>"",33.33%, 0))) -> 0.6667 | T14: JC | W14: On-Site Power Supply & Transmission | X14: 33kV Main Consumer Plant Switchgear | AB14: Pending
A15: 6105A | B15: K124 | C15: 6243 | D15: E | E15: DST | F15: 0003 | G15: 0 | H15: =A15&B15&"-"&C15&"-"&D15&E15&"-"&F15 -> 6105AK124-6243-EDST-0003 | I15: ="Q24050972"&"-"&"06"&"-"&C15&"-"&D15&"-"&E15&"-"&F15 -> Q24050972-06-6243-E-DST-0003 | K15: =VLOOKUP(C15,'PPE WBS Codes'!$E$3:$F$79,2,0) -> 220/33 kV Plant Main Substation | L15: On-Site Power Supply & Distribution - 33kV Indoor Switchgear | M15: Datasheet | N15: =K15&" - "&L15&" - "&M15 -> 220/33 kV Plant Main Substation - On-Site Power Supply & Distribution - 33kV Indoor Switchgear - Datasheet | O15: 45959 | P15: 46153 | Q15: =IFERROR(VLOOKUP(PPE_PH1_CDDL[[#This Row],[RDMC Document Number]],[3]Docs!$B:$F,4,0),"No Placeholder Yet") -> IFU - Issued for Use | R15: =IFERROR(VLOOKUP(PPE_PH1_CDDL[[#This Row],[RDMC Document Number]],[3]Docs!$B:$F,5,0),"No Placeholder Yet") -> Rejected - Revise & Resubmit | S15: =IF(AND(O15<>"",P15<>"",R15="Approved"),100%, IF(AND(O15<>"",P15<>""),66.67%, IF(O15<>"",33.33%, 0))) -> 0.6667 | T15: JC | W15: On-Site Power Supply & Distribution | X15: 33kV Indoor Switchgear | AB15: Pending
A16: 6105A | B16: K124 | C16: 6243 | D16: E | E16: DST | F16: 0004 | G16: A | H16: =A16&B16&"-"&C16&"-"&D16&E16&"-"&F16 -> 6105AK124-6243-EDST-0004 | I16: ="Q24050972"&"-"&"06"&"-"&C16&"-"&D16&"-"&E16&"-"&F16 -> Q24050972-06-6243-E-DST-0004 | K16: =VLOOKUP(C16,'PPE WBS Codes'!$E$3:$F$79,2,0) -> 220/33 kV Plant Main Substation | L16: 33kV Distribution Switch Rooms - 4 x Battery Tripping Units (110V DC) | M16: Datasheet | N16: =K16&" - "&L16&" - "&M16 -> 220/33 kV Plant Main Substation - 33kV Distribution Switch Rooms - 4 x Battery Tripping Units (110V DC) - Datasheet | Q16: =IFERROR(VLOOKUP(PPE_PH1_CDDL[[#This Row],[RDMC Document Number]],[3]Docs!$B:$F,4,0),"No Placeholder Yet") -> RES - Reserved Placeholder | R16: =IFERROR(VLOOKUP(PPE_PH1_CDDL[[#This Row],[RDMC Document Number]],[3]Docs!$B:$F,5,0),"No Placeholder Yet") -> Pending | S16: =IF(AND(O16<>"",P16<>"",R16="Approved"),100%, IF(AND(O16<>"",P16<>""),66.67%, IF(O16<>"",33.33%, 0))) -> 0 | T16: JC | V16: TENDER | W16: Battery Tripping Units | X16: Datasheet | AB16: Pending
A17: 6105A | B17: K124 | C17: 6243 | D17: E | E17: DST | F17: 0005 | G17: A | H17: =A17&B17&"-"&C17&"-"&D17&E17&"-"&F17 -> 6105AK124-6243-EDST-0005 | I17: ="Q24050972"&"-"&"06"&"-"&C17&"-"&D17&"-"&E17&"-"&F17 -> Q24050972-06-6243-E-DST-0005 | K17: =VLOOKUP(C17,'PPE WBS Codes'!$E$3:$F$79,2,0) -> 220/33 kV Plant Main Substation | L17: Specification for 300mm², 33kV, Single-Core, Unarmored Aluminium Cable | M17: Datasheet | N17: =K17&" - "&L17&" - "&M17 -> 220/33 kV Plant Main Substation - Specification for 300mm², 33kV, Single-Core, Unarmored Aluminium Cable - Datasheet | Q17: =IFERROR(VLOOKUP(PPE_PH1_CDDL[[#This Row],[RDMC Document Number]],[3]Docs!$B:$F,4,0),"No Placeholder Yet") -> RES - Reserved Placeholder | R17: =IFERROR(VLOOKUP(PPE_PH1_CDDL[[#This Row],[RDMC Document Number]],[3]Docs!$B:$F,5,0),"No Placeholder Yet") -> Pending | S17: =IF(AND(O17<>"",P17<>"",R17="Approved"),100%, IF(AND(O17<>"",P17<>""),66.67%, IF(O17<>"",33.33%, 0))) -> 0 | T17: JC | V17: TENDER | W17: Specification for 300mm² | X17: 33kV, Single-Core, Unarmored Aluminium Cable | AB17: Pending
A18: 6105A | B18: K124 | C18: 6250 | D18: E | E18: DST | F18: 0001 | G18: A | H18: =A18&B18&"-"&C18&"-"&D18&E18&"-"&F18 -> 6105AK124-6250-EDST-0001 | I18: ="Q24050972"&"-"&"07"&"-"&C18&"-"&D18&"-"&E18&"-"&F18 -> Q24050972-07-6250-E-DST-0001 | K18: =VLOOKUP(C18,'PPE WBS Codes'!$E$3:$F$79,2,0) -> Power Conditioning Equipment | L18: Synchronous Condenser and Excitation System | M18: Datasheet | N18: =K18&" - "&L18&" - "&M18 -> Power Conditioning Equipment - Synchronous Condenser and Excitation System - Datasheet | Q18: =IFERROR(VLOOKUP(PPE_PH1_CDDL[[#This Row],[RDMC Document Number]],[3]Docs!$B:$F,4,0),"No Placeholder Yet") -> RES - Reserved Placeholder | R18: =IFERROR(VLOOKUP(PPE_PH1_CDDL[[#This Row],[RDMC Document Number]],[3]Docs!$B:$F,5,0),"No Placeholder Yet") -> Pending | S18: =IF(AND(O18<>"",P18<>"",R18="Approved"),100%, IF(AND(O18<>"",P18<>""),66.67%, IF(O18<>"",33.33%, 0))) -> 0 | T18: ET | V18: TENDER | W18: Synchronous Condenser | X18: Datasheet | AB18: Pending
A19: 6105A | B19: K124 | C19: 6260 | D19: E | E19: DST | F19: 0008 | G19: 2 | H19: =A19&B19&"-"&C19&"-"&D19&E19&"-"&F19 -> 6105AK124-6260-EDST-0008 | I19: ="Q24050972"&"-"&"04"&"-"&C19&"-"&D19&"-"&E19&"-"&F19 -> Q24050972-04-6260-E-DST-0008 | K19: =VLOOKUP(C19,'PPE WBS Codes'!$E$3:$F$79,2,0) -> Emergency Power Generation (Main Plant) | L19: Neutral Earthing Compensator Resistor (33kV NECr) | M19: Datasheet | N19: =K19&" - "&L19&" - "&M19 -> Emergency Power Generation (Main Plant) - Neutral Earthing Compensator Resistor (33kV NECr) - Datasheet | O19: 45954 | P19: 46162 | Q19: =IFERROR(VLOOKUP(PPE_PH1_CDDL[[#This Row],[RDMC Document Number]],[3]Docs!$B:$F,4,0),"No Placeholder Yet") -> IFU - Issued for Use | R19: =IFERROR(VLOOKUP(PPE_PH1_CDDL[[#This Row],[RDMC Document Number]],[3]Docs!$B:$F,5,0),"No Placeholder Yet") -> Pending | S19: =IF(AND(O19<>"",P19<>"",R19="Approved"),100%, IF(AND(O19<>"",P19<>""),66.67%, IF(O19<>"",33.33%, 0))) -> 0.6667 | T19: IS | W19: Neutral Earthing Compensator Resistor (33kV NECr) | X19: Datasheet | AB19: Pending
A20: 6105A | B20: K124 | C20: 6260 | D20: E | E20: DST | F20: 0016 | G20: A | H20: =A20&B20&"-"&C20&"-"&D20&E20&"-"&F20 -> 6105AK124-6260-EDST-0016 | I20: ="Q24050972"&"-"&"07"&"-"&C20&"-"&D20&"-"&E20&"-"&F20 -> Q24050972-07-6260-E-DST-0016 | K20: =VLOOKUP(C20,'PPE WBS Codes'!$E$3:$F$79,2,0) -> Emergency Power Generation (Main Plant) | L20: 630kVA Mini-substation (11/0.4kV) | M20: Datasheet | N20: =K20&" - "&L20&" - "&M20 -> Emergency Power Generation (Main Plant) - 630kVA Mini-substation (11/0.4kV) - Datasheet | Q20: =IFERROR(VLOOKUP(PPE_PH1_CDDL[[#This Row],[RDMC Document Number]],[3]Docs!$B:$F,4,0),"No Placeholder Yet") -> RES - Reserved Placeholder | R20: =IFERROR(VLOOKUP(PPE_PH1_CDDL[[#This Row],[RDMC Document Number]],[3]Docs!$B:$F,5,0),"No Placeholder Yet") -> Pending | S20: =IF(AND(O20<>"",P20<>"",R20="Approved"),100%, IF(AND(O20<>"",P20<>""),66.67%, IF(O20<>"",33.33%, 0))) -> 0 | T20: IS | V20: TENDER | W20: Substation | X20: Datasheet | AB20: Pending
A21: 6105A | B21: K124 | C21: 6262 | D21: E | E21: DST | F21: 0004 | G21: A | H21: =A21&B21&"-"&C21&"-"&D21&E21&"-"&F21 -> 6105AK124-6262-EDST-0004 | I21: ="Q24050972"&"-"&"08"&"-"&C21&"-"&D21&"-"&E21&"-"&F21 -> Q24050972-08-6262-E-DST-0004 | J21: Sht 1 of 1 | K21: Emergency Power Generation | L21: 11kVA MV E-house type 1B | M21: Internal Views | N21: =K21&" - "&L21&" - "&M21&" - "&J21 -> Emergency Power Generation - 11kVA MV E-house type 1B - Internal Views - Sht 1 of 1 | Q21: =IFERROR(VLOOKUP(PPE_PH1_CDDL[[#This Row],[RDMC Document Number]],[3]Docs!$B:$F,4,0),"No Placeholder Yet") -> RES - Reserved Placeholder | R21: =IFERROR(VLOOKUP(PPE_PH1_CDDL[[#This Row],[RDMC Document Number]],[3]Docs!$B:$F,5,0),"No Placeholder Yet") -> Pending | S21: =IF(AND(O21<>"",P21<>"",R21="Approved"),100%, IF(AND(O21<>"",P21<>""),66.67%, IF(O21<>"",33.33%, 0))) -> 0 | T21: IS | V21: TENDER | W21: 11kVA MV E-house type 1B | X21: MV Control Room | AB21: Pending
A22: 6105A | B22: K124 | C22: 6262 | D22: E | E22: DST | F22: 0001 | G22: A | H22: =A22&B22&"-"&C22&"-"&D22&E22&"-"&F22 -> 6105AK124-6262-EDST-0001 | I22: ="Q24050972"&"-"&"07"&"-"&C22&"-"&D22&"-"&E22&"-"&F22 -> Q24050972-07-6262-E-DST-0001 | K22: =VLOOKUP(C22,'PPE WBS Codes'!$E$3:$F$79,2,0) -> Emergency Power Substation 1 and Control Room 1 | L22: Auxiliary 400V AC Panel | M22: Datasheet | N22: =K22&" - "&L22&" - "&M22 -> Emergency Power Substation 1 and Control Room 1 - Auxiliary 400V AC Panel - Datasheet | Q22: =IFERROR(VLOOKUP(PPE_PH1_CDDL[[#This Row],[RDMC Document Number]],[3]Docs!$B:$F,4,0),"No Placeholder Yet") -> RES - Reserved Placeholder | R22: =IFERROR(VLOOKUP(PPE_PH1_CDDL[[#This Row],[RDMC Document Number]],[3]Docs!$B:$F,5,0),"No Placeholder Yet") -> Pending | S22: =IF(AND(O22<>"",P22<>"",R22="Approved"),100%, IF(AND(O22<>"",P22<>""),66.67%, IF(O22<>"",33.33%, 0))) -> 0 | T22: IS | V22: TENDER | W22: Auxiliary 400V AC Panel | X22: Datasheet | AB22: Pending
A23: 6105A | B23: K124 | C23: 6262 | D23: E | E23: DST | F23: 0002 | G23: 0 | H23: =A23&B23&"-"&C23&"-"&D23&E23&"-"&F23 -> 6105AK124-6262-EDST-0002 | I23: ="Q24050972"&"-"&"07"&"-"&C23&"-"&D23&"-"&E23&"-"&F23 -> Q24050972-07-6262-E-DST-0002 | K23: =VLOOKUP(C23,'PPE WBS Codes'!$E$3:$F$79,2,0) -> Emergency Power Substation 1 and Control Room 1 | L23: Auxiliary 230V AC Battery Back-up Supply | M23: Datasheet | N23: =K23&" - "&L23&" - "&M23 -> Emergency Power Substation 1 and Control Room 1 - Auxiliary 230V AC Battery Back-up Supply - Datasheet | O23: 45956 | P23: 45968 | Q23: =IFERROR(VLOOKUP(PPE_PH1_CDDL[[#This Row],[RDMC Document Number]],[3]Docs!$B:$F,4,0),"No Placeholder Yet") -> IFD - Issued for Design | R23: =IFERROR(VLOOKUP(PPE_PH1_CDDL[[#This Row],[RDMC Document Number]],[3]Docs!$B:$F,5,0),"No Placeholder Yet") -> Approved | S23: =IF(AND(O23<>"",P23<>"",R23="Approved"),100%, IF(AND(O23<>"",P23<>""),66.67%, IF(O23<>"",33.33%, 0))) -> 1 | T23: IS | U23: Approved | W23: Auxiliary 230V AC Battery Back-up Supply | X23: Datasheet | AB23: Pending
A24: 6105A | B24: K124 | C24: 6262 | D24: E | E24: DST | F24: 0003 | G24: 1 | H24: =A24&B24&"-"&C24&"-"&D24&E24&"-"&F24 -> 6105AK124-6262-EDST-0003 | I24: ="Q24050972"&"-"&"07"&"-"&C24&"-"&D24&"-"&E24&"-"&F24 -> Q24050972-07-6262-E-DST-0003 | K24: =VLOOKUP(C24,'PPE WBS Codes'!$E$3:$F$79,2,0) -> Emergency Power Substation 1 and Control Room 1 | L24: 11kV MV Switchgear | M24: Datasheet | N24: =K24&" - "&L24&" - "&M24 -> Emergency Power Substation 1 and Control Room 1 - 11kV MV Switchgear - Datasheet | O24: 45952 | P24: 45994 | Q24: =IFERROR(VLOOKUP(PPE_PH1_CDDL[[#This Row],[RDMC Document Number]],[3]Docs!$B:$F,4,0),"No Placeholder Yet") -> IFU - Issued for Use | R24: =IFERROR(VLOOKUP(PPE_PH1_CDDL[[#This Row],[RDMC Document Number]],[3]Docs!$B:$F,5,0),"No Placeholder Yet") -> Approved | S24: =IF(AND(O24<>"",P24<>"",R24="Approved"),100%, IF(AND(O24<>"",P24<>""),66.67%, IF(O24<>"",33.33%, 0))) -> 1 | T24: IS | U24: Approved | W24: 11kV MV Switchgear | X24: Datasheet | AB24: Pending
A25: 6105A | B25: K124 | C25: 6263 | D25: E | E25: DST | F25: 0002 | G25: A | H25: =A25&B25&"-"&C25&"-"&D25&E25&"-"&F25 -> 6105AK124-6263-EDST-0002 | I25: ="Q24050972"&"-"&"07"&"-"&C25&"-"&D25&"-"&E25&"-"&F25 -> Q24050972-07-6263-E-DST-0002 | K25: =VLOOKUP(C25,'PPE WBS Codes'!$E$3:$F$79,2,0) -> 36 MVA Power Station 1 | L25: 20 MW 11kV Load Banks | M25: Datasheet | N25: =K25&" - "&L25&" - "&M25 -> 36 MVA Power Station 1 - 20 MW 11kV Load Banks - Datasheet | Q25: =IFERROR(VLOOKUP(PPE_PH1_CDDL[[#This Row],[RDMC Document Number]],[3]Docs!$B:$F,4,0),"No Placeholder Yet") -> RES - Reserved Placeholder | R25: =IFERROR(VLOOKUP(PPE_PH1_CDDL[[#This Row],[RDMC Document Number]],[3]Docs!$B:$F,5,0),"No Placeholder Yet") -> Pending | S25: =IF(AND(O25<>"",P25<>"",R25="Approved"),100%, IF(AND(O25<>"",P25<>""),66.67%, IF(O25<>"",33.33%, 0))) -> 0 | T25: JC | V25: TENDER | W25: 20 MW 11kV Load banks | X25: Datasheet | AB25: Pending
A26: 6105A | B26: K124 | C26: 6263 | D26: E | E26: DST | F26: 0003 | G26: 0 | H26: =A26&B26&"-"&C26&"-"&D26&E26&"-"&F26 -> 6105AK124-6263-EDST-0003 | I26: ="Q24050972"&"-"&"07"&"-"&C26&"-"&D26&"-"&E26&"-"&F26 -> Q24050972-07-6263-E-DST-0003 | K26: =VLOOKUP(C26,'PPE WBS Codes'!$E$3:$F$79,2,0) -> 36 MVA Power Station 1 | L26: High Speed Diesel Generators | M26: Datasheet | N26: =K26&" - "&L26&" - "&M26 -> 36 MVA Power Station 1 - High Speed Diesel Generators - Datasheet | O26: 45956 | P26: 45979 | Q26: =IFERROR(VLOOKUP(PPE_PH1_CDDL[[#This Row],[RDMC Document Number]],[3]Docs!$B:$F,4,0),"No Placeholder Yet") -> IFD - Issued for Design | R26: =IFERROR(VLOOKUP(PPE_PH1_CDDL[[#This Row],[RDMC Document Number]],[3]Docs!$B:$F,5,0),"No Placeholder Yet") -> Pending | S26: =IF(AND(O26<>"",P26<>"",R26="Approved"),100%, IF(AND(O26<>"",P26<>""),66.67%, IF(O26<>"",33.33%, 0))) -> 0.6667 | T26: IS | W26: High Speed Diesel Generators | X26: Datasheet | AB26: Pending
A27: 6105A | B27: K124 | C27: 6263 | D27: E | E27: DST | F27: 0004 | G27: 0 | H27: =A27&B27&"-"&C27&"-"&D27&E27&"-"&F27 -> 6105AK124-6263-EDST-0004 | I27: ="Q24050972"&"-"&"07"&"-"&C27&"-"&D27&"-"&E27&"-"&F27 -> Q24050972-07-6263-E-DST-0004 | K27: =VLOOKUP(C27,'PPE WBS Codes'!$E$3:$F$79,2,0) -> 36 MVA Power Station 1 | L27: Neutral Earthing Resistor (11kV NER) | M27: Datasheet | N27: =K27&" - "&L27&" - "&M27 -> 36 MVA Power Station 1 - Neutral Earthing Resistor (11kV NER) - Datasheet | O27: 45956 | P27: 45968 | Q27: =IFERROR(VLOOKUP(PPE_PH1_CDDL[[#This Row],[RDMC Document Number]],[3]Docs!$B:$F,4,0),"No Placeholder Yet") -> IFD - Issued for Design | R27: =IFERROR(VLOOKUP(PPE_PH1_CDDL[[#This Row],[RDMC Document Number]],[3]Docs!$B:$F,5,0),"No Placeholder Yet") -> Approved | S27: =IF(AND(O27<>"",P27<>"",R27="Approved"),100%, IF(AND(O27<>"",P27<>""),66.67%, IF(O27<>"",33.33%, 0))) -> 1 | T27: IS | U27: Approved | W27: Neutral Earthing Resistor (11kV NER) | X27: Datasheet | AB27: Pending
A28: 6105A | B28: K124 | C28: 6263 | D28: E | E28: DST | F28: 0005 | G28: A | H28: =A28&B28&"-"&C28&"-"&D28&E28&"-"&F28 -> 6105AK124-6263-EDST-0005 | I28: ="Q24050972"&"-"&"07"&"-"&C28&"-"&D28&"-"&E28&"-"&F28 -> Q24050972-07-6263-E-DST-0005 | K28: =VLOOKUP(C28,'PPE WBS Codes'!$E$3:$F$79,2,0) -> 36 MVA Power Station 1 | L28: 11kV RMU for Load Banks | M28: Datasheet | N28: =K28&" - "&L28&" - "&M28 -> 36 MVA Power Station 1 - 11kV RMU for Load Banks - Datasheet | Q28: =IFERROR(VLOOKUP(PPE_PH1_CDDL[[#This Row],[RDMC Document Number]],[3]Docs!$B:$F,4,0),"No Placeholder Yet") -> RES - Reserved Placeholder | R28: =IFERROR(VLOOKUP(PPE_PH1_CDDL[[#This Row],[RDMC Document Number]],[3]Docs!$B:$F,5,0),"No Placeholder Yet") -> Pending | S28: =IF(AND(O28<>"",P28<>"",R28="Approved"),100%, IF(AND(O28<>"",P28<>""),66.67%, IF(O28<>"",33.33%, 0))) -> 0 | T28: JC | V28: TENDER | W28: 11kV RMU for Load Banks | X28: Datasheet | AB28: Pending
A29: 6105A | B29: K124 | C29: 6264 | D29: E | E29: DST | F29: 0001 | G29: A | H29: =A29&B29&"-"&C29&"-"&D29&E29&"-"&F29 -> 6105AK124-6264-EDST-0001 | I29: ="Q24050972"&"-"&"08"&"-"&C29&"-"&D29&"-"&E29&"-"&F29 -> Q24050972-08-6264-E-DST-0001 | K29: =VLOOKUP(C29,'PPE WBS Codes'!$E$3:$F$79,2,0) -> Bulk Diesel Storage 1 | L29: Bulk Fuel Tanks | M29: Datasheet | N29: =K29&" - "&L29&" - "&M29 -> Bulk Diesel Storage 1 - Bulk Fuel Tanks - Datasheet | Q29: =IFERROR(VLOOKUP(PPE_PH1_CDDL[[#This Row],[RDMC Document Number]],[3]Docs!$B:$F,4,0),"No Placeholder Yet") -> RES - Reserved Placeholder | R29: =IFERROR(VLOOKUP(PPE_PH1_CDDL[[#This Row],[RDMC Document Number]],[3]Docs!$B:$F,5,0),"No Placeholder Yet") -> Pending | S29: =IF(AND(O29<>"",P29<>"",R29="Approved"),100%, IF(AND(O29<>"",P29<>""),66.67%, IF(O29<>"",33.33%, 0))) -> 0 | T29: IS | V29: TENDER | W29: Bulk Fuel Tanks | X29: Datasheet | AB29: Pending
A30: 6105A | B30: K124 | C30: 6286 | D30: E | E30: DST | F30: 0001 | G30: 0 | H30: =A30&B30&"-"&C30&"-"&D30&E30&"-"&F30 -> 6105AK124-6286-EDST-0001 | I30: ="Q24050972"&"-"&"06"&"-"&C30&"-"&D30&"-"&E30&"-"&F30 -> Q24050972-06-6286-E-DST-0001 | K30: =VLOOKUP(C30,'PPE WBS Codes'!$E$3:$F$79,2,0) -> Primary Crushing | L30: On-Site Power Supply & Transmission_ MV 33kV Mining Sub MV Switchgear | M30: Datasheet | N30: =K30&" - "&L30&" - "&M30 -> Primary Crushing - On-Site Power Supply & Transmission_ MV 33kV Mining Sub MV Switchgear - Datasheet | O30: 45952 | P30: 45968 | Q30: =IFERROR(VLOOKUP(PPE_PH1_CDDL[[#This Row],[RDMC Document Number]],[3]Docs!$B:$F,4,0),"No Placeholder Yet") -> IFD - Issued for Design | R30: =IFERROR(VLOOKUP(PPE_PH1_CDDL[[#This Row],[RDMC Document Number]],[3]Docs!$B:$F,5,0),"No Placeholder Yet") -> Approved | S30: =IF(AND(O30<>"",P30<>"",R30="Approved"),100%, IF(AND(O30<>"",P30<>""),66.67%, IF(O30<>"",33.33%, 0))) -> 1 | T30: JC | U30: Approved | W30: On-Site Power Supply & Transmission | X30: MV 33kV Mining Sub MV Switchgear | AB30: Pending
A31: 6105A | B31: K124 | C31: 6286 | D31: E | E31: DST | F31: 0002 | G31: A | H31: =A31&B31&"-"&C31&"-"&D31&E31&"-"&F31 -> 6105AK124-6286-EDST-0002 | I31: ="Q24050972"&"-"&"07"&"-"&C31&"-"&D31&"-"&E31&"-"&F31 -> Q24050972-07-6286-E-DST-0002 | K31: =VLOOKUP(C31,'PPE WBS Codes'!$E$3:$F$79,2,0) -> Primary Crushing | L31: 11kV Substation | M31: Datasheet | N31: =K31&" - "&L31&" - "&M31 -> Primary Crushing - 11kV Substation - Datasheet | Q31: =IFERROR(VLOOKUP(PPE_PH1_CDDL[[#This Row],[RDMC Document Number]],[3]Docs!$B:$F,4,0),"No Placeholder Yet") -> RES - Reserved Placeholder | R31: =IFERROR(VLOOKUP(PPE_PH1_CDDL[[#This Row],[RDMC Document Number]],[3]Docs!$B:$F,5,0),"No Placeholder Yet") -> Pending | S31: =IF(AND(O31<>"",P31<>"",R31="Approved"),100%, IF(AND(O31<>"",P31<>""),66.67%, IF(O31<>"",33.33%, 0))) -> 0 | T31: JC | V31: TENDER | W31: 11kV Substation | X31: Datasheet | AB31: Pending
A32: 6105A | B32: K124 | C32: 6286 | D32: E | E32: DST | F32: 0003 | G32: A | H32: =A32&B32&"-"&C32&"-"&D32&E32&"-"&F32 -> 6105AK124-6286-EDST-0003 | I32: ="Q24050972"&"-"&"07"&"-"&C32&"-"&D32&"-"&E32&"-"&F32 -> Q24050972-07-6286-E-DST-0003 | K32: =VLOOKUP(C32,'PPE WBS Codes'!$E$3:$F$79,2,0) -> Primary Crushing | L32: Auxiliary 400Vac Distribution Board | M32: Datasheet | N32: =K32&" - "&L32&" - "&M32 -> Primary Crushing - Auxiliary 400Vac Distribution Board - Datasheet | Q32: =IFERROR(VLOOKUP(PPE_PH1_CDDL[[#This Row],[RDMC Document Number]],[3]Docs!$B:$F,4,0),"No Placeholder Yet") -> RES - Reserved Placeholder | R32: =IFERROR(VLOOKUP(PPE_PH1_CDDL[[#This Row],[RDMC Document Number]],[3]Docs!$B:$F,5,0),"No Placeholder Yet") -> Pending | S32: =IF(AND(O32<>"",P32<>"",R32="Approved"),100%, IF(AND(O32<>"",P32<>""),66.67%, IF(O32<>"",33.33%, 0))) -> 0 | T32: IS | V32: TENDER | W32: Auxiliary 400Vac Distribution Board | X32: Datasheet | AB32: Pending
A33: 6105A | B33: K124 | C33: 6286 | D33: E | E33: DST | F33: 0004 | G33: 0 | H33: =A33&B33&"-"&C33&"-"&D33&E33&"-"&F33 -> 6105AK124-6286-EDST-0004 | I33: ="Q24050972"&"-"&"07"&"-"&C33&"-"&D33&"-"&E33&"-"&F33 -> Q24050972-07-6286-E-DST-0004 | K33: =VLOOKUP(C33,'PPE WBS Codes'!$E$3:$F$79,2,0) -> Primary Crushing | L33: 11kV Switchgear | M33: Datasheet | N33: =K33&" - "&L33&" - "&M33 -> Primary Crushing - 11kV Switchgear - Datasheet | O33: 45980 | P33: 45991 | Q33: =IFERROR(VLOOKUP(PPE_PH1_CDDL[[#This Row],[RDMC Document Number]],[3]Docs!$B:$F,4,0),"No Placeholder Yet") -> IFD - Issued for Design | R33: =IFERROR(VLOOKUP(PPE_PH1_CDDL[[#This Row],[RDMC Document Number]],[3]Docs!$B:$F,5,0),"No Placeholder Yet") -> Pending | S33: =IF(AND(O33<>"",P33<>"",R33="Approved"),100%, IF(AND(O33<>"",P33<>""),66.67%, IF(O33<>"",33.33%, 0))) -> 0.6667 | T33: IS | V33: TENDER | W33: 11KV Switchgear | X33: Datasheet | AB33: Pending
A34: 6105A | B34: K124 | C34: 6292 | D34: E | E34: DST | F34: 0001 | G34: A | H34: =A34&B34&"-"&C34&"-"&D34&E34&"-"&F34 -> 6105AK124-6292-EDST-0001 | I34: ="Q24050972"&"-"&"07"&"-"&C34&"-"&D34&"-"&E34&"-"&F34 -> Q24050972-07-6292-E-DST-0001 | K34: =VLOOKUP(C34,'PPE WBS Codes'!$E$3:$F$79,2,0) -> 11/33 kV Solar PV Substation 1 and Control Room 1 | L34: 33kV Indoor Switchgear | M34: Datasheet | N34: =K34&" - "&L34&" - "&M34 -> 11/33 kV Solar PV Substation 1 and Control Room 1 - 33kV Indoor Switchgear - Datasheet | Q34: =IFERROR(VLOOKUP(PPE_PH1_CDDL[[#This Row],[RDMC Document Number]],[3]Docs!$B:$F,4,0),"No Placeholder Yet") -> RES - Reserved Placeholder | R34: =IFERROR(VLOOKUP(PPE_PH1_CDDL[[#This Row],[RDMC Document Number]],[3]Docs!$B:$F,5,0),"No Placeholder Yet") -> Pending | S34: =IF(AND(O34<>"",P34<>"",R34="Approved"),100%, IF(AND(O34<>"",P34<>""),66.67%, IF(O34<>"",33.33%, 0))) -> 0 | T34: JC | V34: TENDER | W34: 33kV Indoor Switchgear | X34: Datasheet | AB34: Pending
A35: 6105A | B35: K124 | C35: 6292 | D35: E | E35: DST | F35: 0002 | G35: A | H35: =A35&B35&"-"&C35&"-"&D35&E35&"-"&F35 -> 6105AK124-6292-EDST-0002 | I35: ="Q24050972"&"-"&"07"&"-"&C35&"-"&D35&"-"&E35&"-"&F35 -> Q24050972-07-6292-E-DST-0002 | K35: =VLOOKUP(C35,'PPE WBS Codes'!$E$3:$F$79,2,0) -> 11/33 kV Solar PV Substation 1 and Control Room 1 | L35: 3x Battery Tripping Units 9110V DC | M35: Datasheet | N35: =K35&" - "&L35&" - "&M35 -> 11/33 kV Solar PV Substation 1 and Control Room 1 - 3x Battery Tripping Units 9110V DC - Datasheet | Q35: =IFERROR(VLOOKUP(PPE_PH1_CDDL[[#This Row],[RDMC Document Number]],[3]Docs!$B:$F,4,0),"No Placeholder Yet") -> RES - Reserved Placeholder | R35: =IFERROR(VLOOKUP(PPE_PH1_CDDL[[#This Row],[RDMC Document Number]],[3]Docs!$B:$F,5,0),"No Placeholder Yet") -> Pending | S35: =IF(AND(O35<>"",P35<>"",R35="Approved"),100%, IF(AND(O35<>"",P35<>""),66.67%, IF(O35<>"",33.33%, 0))) -> 0 | T35: JC | V35: TENDER | W35: 3x Battery Tripping Units 9110V DC | X35: Datasheet | AB35: Pending
A36: 6105A | B36: K124 | C36: 6292 | D36: E | E36: DST | F36: 0003 | G36: A | H36: =A36&B36&"-"&C36&"-"&D36&E36&"-"&F36 -> 6105AK124-6292-EDST-0003 | I36: ="Q24050972"&"-"&"07"&"-"&C36&"-"&D36&"-"&E36&"-"&F36 -> Q24050972-07-6292-E-DST-0003 | K36: =VLOOKUP(C36,'PPE WBS Codes'!$E$3:$F$79,2,0) -> 11/33 kV Solar PV Substation 1 and Control Room 1 | L36: MV 33kV Solar Plant Sub StationSwitchgear | M36: Datasheet | N36: =K36&" - "&L36&" - "&M36 -> 11/33 kV Solar PV Substation 1 and Control Room 1 - MV 33kV Solar Plant Sub StationSwitchgear - Datasheet | Q36: =IFERROR(VLOOKUP(PPE_PH1_CDDL[[#This Row],[RDMC Document Number]],[3]Docs!$B:$F,4,0),"No Placeholder Yet") -> RES - Reserved Placeholder | R36: =IFERROR(VLOOKUP(PPE_PH1_CDDL[[#This Row],[RDMC Document Number]],[3]Docs!$B:$F,5,0),"No Placeholder Yet") -> Pending | S36: =IF(AND(O36<>"",P36<>"",R36="Approved"),100%, IF(AND(O36<>"",P36<>""),66.67%, IF(O36<>"",33.33%, 0))) -> 0 | T36: JC | V36: TENDER | W36: MV 33kV Solar Plant | X36: Sub Station Switchgear | AB36: Pending
A37: 6105A | B37: K124 | C37: 6292 | D37: E | E37: DST | F37: 0004 | G37: A | H37: =A37&B37&"-"&C37&"-"&D37&E37&"-"&F37 -> 6105AK124-6292-EDST-0004 | I37: ="Q24050972"&"-"&"08"&"-"&C37&"-"&D37&"-"&E37&"-"&F37 -> Q24050972-08-6292-E-DST-0004 | K37: =VLOOKUP(C37,'PPE WBS Codes'!$E$3:$F$79,2,0) -> 11/33 kV Solar PV Substation 1 and Control Room 1 | L37: Primary Electrical Reticulation Network - Main Consumer Plant Reticulation | M37: Datasheet | N37: =K37&" - "&L37&" - "&M37 -> 11/33 kV Solar PV Substation 1 and Control Room 1 - Primary Electrical Reticulation Network - Main Consumer Plant Reticulation - Datasheet | Q37: =IFERROR(VLOOKUP(PPE_PH1_CDDL[[#This Row],[RDMC Document Number]],[3]Docs!$B:$F,4,0),"No Placeholder Yet") -> RES - Reserved Placeholder | R37: =IFERROR(VLOOKUP(PPE_PH1_CDDL[[#This Row],[RDMC Document Number]],[3]Docs!$B:$F,5,0),"No Placeholder Yet") -> Pending | S37: =IF(AND(O37<>"",P37<>"",R37="Approved"),100%, IF(AND(O37<>"",P37<>""),66.67%, IF(O37<>"",33.33%, 0))) -> 0 | T37: JC | V37: TENDER | W37: Primary Electrical Reticulation Network | X37: Main Consumer Plant Reticulation | AB37: Pending
A38: 6105A | B38: K124 | C38: 0100 | D38: E | E38: DST | F38: 0002 | G38: A | H38: =A38&B38&"-"&C38&"-"&D38&E38&"-"&F38 -> 6105AK124-0100-EDST-0002 | I38: ="Q24050972"&"-"&"07"&"-"&C38&"-"&D38&"-"&E38&"-"&F38 -> Q24050972-07-0100-E-DST-0002 | K38: =VLOOKUP(C38,'PPE WBS Codes'!$E$3:$F$79,2,0) -> Project Site Wide | L38: Pressurisation Fan - MV Switch Rooms | M38: Datasheet | N38: =K38&" - "&L38&" - "&M38 -> Project Site Wide - Pressurisation Fan - MV Switch Rooms - Datasheet | Q38: =IFERROR(VLOOKUP(PPE_PH1_CDDL[[#This Row],[RDMC Document Number]],[3]Docs!$B:$F,4,0),"No Placeholder Yet") -> RES - Reserved Placeholder | R38: =IFERROR(VLOOKUP(PPE_PH1_CDDL[[#This Row],[RDMC Document Number]],[3]Docs!$B:$F,5,0),"No Placeholder Yet") -> Pending | S38: =IF(AND(O38<>"",P38<>"",R38="Approved"),100%, IF(AND(O38<>"",P38<>""),66.67%, IF(O38<>"",33.33%, 0))) -> 0 | T38: IS | V38: TENDER | W38: Pressurisation Fan | X38: MV Switch Rooms | AB38: Pending
A39: 6105A | B39: K124 | C39: 0100 | D39: E | E39: DST | F39: 0003 | G39: A | H39: =A39&B39&"-"&C39&"-"&D39&E39&"-"&F39 -> 6105AK124-0100-EDST-0003 | I39: ="Q24050972"&"-"&"07"&"-"&C39&"-"&D39&"-"&E39&"-"&F39 -> Q24050972-07-0100-E-DST-0003 | K39: =VLOOKUP(C39,'PPE WBS Codes'!$E$3:$F$79,2,0) -> Project Site Wide | L39: Extraction Fan - MV Control Room | M39: Datasheet | N39: =K39&" - "&L39&" - "&M39 -> Project Site Wide - Extraction Fan - MV Control Room - Datasheet | Q39: =IFERROR(VLOOKUP(PPE_PH1_CDDL[[#This Row],[RDMC Document Number]],[3]Docs!$B:$F,4,0),"No Placeholder Yet") -> RES - Reserved Placeholder | R39: =IFERROR(VLOOKUP(PPE_PH1_CDDL[[#This Row],[RDMC Document Number]],[3]Docs!$B:$F,5,0),"No Placeholder Yet") -> Pending | S39: =IF(AND(O39<>"",P39<>"",R39="Approved"),100%, IF(AND(O39<>"",P39<>""),66.67%, IF(O39<>"",33.33%, 0))) -> 0 | T39: IS | V39: TENDER | W39: Extraction Fan | X39: MV Control Room | AB39: Pending
A40: 6105A | B40: K124 | C40: 6260 | D40: E | E40: DST | F40: 0017 | G40: A | H40: =A40&B40&"-"&C40&"-"&D40&E40&"-"&F40 -> 6105AK124-6260-EDST-0017 | I40: ="Q24050972"&"-"&"07"&"-"&C40&"-"&D40&"-"&E40&"-"&F40 -> Q24050972-07-6260-E-DST-0017 | J40: Sht 1 of 1 | K40: =VLOOKUP(C40,'PPE WBS Codes'!$E$3:$F$79,2,0) -> Emergency Power Generation (Main Plant) | L40: Bulk Fuel Storage 1 | M40: Datasheet | N40: =K40&" - "&L40&" - "&M40&" - "&J40 -> Emergency Power Generation (Main Plant) - Bulk Fuel Storage 1 - Datasheet - Sht 1 of 1 | Q40: =IFERROR(VLOOKUP(PPE_PH1_CDDL[[#This Row],[RDMC Document Number]],[3]Docs!$B:$F,4,0),"No Placeholder Yet") -> RES - Reserved Placeholder | R40: =IFERROR(VLOOKUP(PPE_PH1_CDDL[[#This Row],[RDMC Document Number]],[3]Docs!$B:$F,5,0),"No Placeholder Yet") -> Pending | S40: =IF(AND(O40<>"",P40<>"",R40="Approved"),100%, IF(AND(O40<>"",P40<>""),66.67%, IF(O40<>"",33.33%, 0))) -> 0 | T40: IS | V40: TENDER | W40: Bulk Fuel Storage 1 | X40: Datasheet | AB40: Pending
A41: 6105A | B41: K124 | C41: 0100 | D41: H | E41: DST | F41: 0001 | G41: A | H41: =A41&B41&"-"&C41&"-"&D41&E41&"-"&F41 -> 6105AK124-0100-HDST-0001 | I41: ="Q24050972"&"-"&"09"&"-"&C41&"-"&D41&"-"&E41&"-"&F41 -> Q24050972-09-0100-H-DST-0001 | K41: =VLOOKUP(C41,'PPE WBS Codes'!$E$3:$F$79,2,0) -> Project Site Wide | L41: Critical Lift | M41: Datasheet | N41: =K41&" - "&L41&" - "&M41 -> Project Site Wide - Critical Lift - Datasheet | Q41: =IFERROR(VLOOKUP(PPE_PH1_CDDL[[#This Row],[RDMC Document Number]],[3]Docs!$B:$F,4,0),"No Placeholder Yet") -> RES - Reserved Placeholder | R41: =IFERROR(VLOOKUP(PPE_PH1_CDDL[[#This Row],[RDMC Document Number]],[3]Docs!$B:$F,5,0),"No Placeholder Yet") -> Pending | S41: =IF(AND(O41<>"",P41<>"",R41="Approved"),100%, IF(AND(O41<>"",P41<>""),66.67%, IF(O41<>"",33.33%, 0))) -> 0 | T41: FV | V41: 46188 | W41: Critical Lift | X41: Datasheet | AB41: Pending
A42: 6105A | B42: K124 | C42: 0100 | D42: H | E42: DST | F42: 0002 | G42: A | H42: =A42&B42&"-"&C42&"-"&D42&E42&"-"&F42 -> 6105AK124-0100-HDST-0002 | I42: ="Q24050972"&"-"&"09"&"-"&C42&"-"&D42&"-"&E42&"-"&F42 -> Q24050972-09-0100-H-DST-0002 | K42: =VLOOKUP(C42,'PPE WBS Codes'!$E$3:$F$79,2,0) -> Project Site Wide | L42: Personnel Lift | M42: Datasheet | N42: =K42&" - "&L42&" - "&M42 -> Project Site Wide - Personnel Lift - Datasheet | Q42: =IFERROR(VLOOKUP(PPE_PH1_CDDL[[#This Row],[RDMC Document Number]],[3]Docs!$B:$F,4,0),"No Placeholder Yet") -> RES - Reserved Placeholder | R42: =IFERROR(VLOOKUP(PPE_PH1_CDDL[[#This Row],[RDMC Document Number]],[3]Docs!$B:$F,5,0),"No Placeholder Yet") -> Pending | S42: =IF(AND(O42<>"",P42<>"",R42="Approved"),100%, IF(AND(O42<>"",P42<>""),66.67%, IF(O42<>"",33.33%, 0))) -> 0 | T42: FV | V42: 46188 | W42: Personnel Lift | X42: Datasheet | AB42: Pending
A43: 6105A | B43: K124 | C43: 6260 | D43: E | E43: DST | F43: 0019 | G43: A | H43: =A43&B43&"-"&C43&"-"&D43&E43&"-"&F43 -> 6105AK124-6260-EDST-0019 | I43: ="Q24050972"&"-"&"10"&"-"&C43&"-"&D43&"-"&E43&"-"&F43 -> Q24050972-10-6260-E-DST-0019 | J43: Sht 1 of 2 | K43: =VLOOKUP(C43,'PPE WBS Codes'!$E$3:$F$79,2,0) -> Emergency Power Generation (Main Plant) | L43: Syncon | M43: Power Transformer - 33kV - NER | N43: =K43&" - "&L43&" - "&M43&" - "&J43 -> Emergency Power Generation (Main Plant) - Syncon - Power Transformer - 33kV - NER - Sht 1 of 2 | Q43: =IFERROR(VLOOKUP(PPE_PH1_CDDL[[#This Row],[RDMC Document Number]],[3]Docs!$B:$F,4,0),"No Placeholder Yet") -> RES - Reserved Placeholder | R43: =IFERROR(VLOOKUP(PPE_PH1_CDDL[[#This Row],[RDMC Document Number]],[3]Docs!$B:$F,5,0),"No Placeholder Yet") -> Pending | S43: =IF(AND(O43<>"",P43<>"",R43="Approved"),100%, IF(AND(O43<>"",P43<>""),66.67%, IF(O43<>"",33.33%, 0))) -> 0 | T43: IS | V43: 46157 | W43: Power Transformer - 33kV - NER | X43: Datasheet | AB43: Pending
A44: 6105A | B44: K124 | C44: 6262 | D44: E | E44: DST | F44: 0005 | G44: A | H44: =A44&B44&"-"&C44&"-"&D44&E44&"-"&F44 -> 6105AK124-6262-EDST-0005 | I44: ="Q24050972"&"-"&"07"&"-"&C44&"-"&D44&"-"&E44&"-"&F44 -> Q24050972-07-6262-E-DST-0005 | J44: Sht 1 of 1 | K44: =VLOOKUP(C44,'PPE WBS Codes'!$E$3:$F$79,2,0) -> Emergency Power Substation 1 and Control Room 1 | L44: MV Switchgear | M44: 11kV MV Switchgear | N44: =K44&" - "&L44&" - "&M44&" - "&J44 -> Emergency Power Substation 1 and Control Room 1 - MV Switchgear - 11kV MV Switchgear - Sht 1 of 1 | Q44: =IFERROR(VLOOKUP(PPE_PH1_CDDL[[#This Row],[RDMC Document Number]],[3]Docs!$B:$F,4,0),"No Placeholder Yet") -> RES - Reserved Placeholder | R44: =IFERROR(VLOOKUP(PPE_PH1_CDDL[[#This Row],[RDMC Document Number]],[3]Docs!$B:$F,5,0),"No Placeholder Yet") -> Pending | S44: =IF(AND(O44<>"",P44<>"",R44="Approved"),100%, IF(AND(O44<>"",P44<>""),66.67%, IF(O44<>"",33.33%, 0))) -> 0 | T44: IS | V44: 46157 | W44: MV Switchgear | X44: 11kV MV Switchgear | AB44: Pending
A45: 6105A | B45: K124 | C45: 0100 | D45: E | E45: DST | F45: 0004 | G45: 0 | H45: =A45&B45&"-"&C45&"-"&D45&E45&"-"&F45 -> 6105AK124-0100-EDST-0004 | I45: ="Q24050972"&"-"&"10"&"-"&C45&"-"&D45&"-"&E45&"-"&F45 -> Q24050972-10-0100-E-DST-0004 | K45: =VLOOKUP(C45,'PPE WBS Codes'!$E$3:$F$79,2,0) -> Project Site Wide | L45: Neutral Earthing Resistor | M45: 11kV Neutral Earthing Resistor (11kV NER) | N45: =K45&" - "&L45&" - "&M45 -> Project Site Wide - Neutral Earthing Resistor - 11kV Neutral Earthing Resistor (11kV NER) | O45: 45964 | P45: 45995 | Q45: =IFERROR(VLOOKUP(PPE_PH1_CDDL[[#This Row],[RDMC Document Number]],[3]Docs!$B:$F,4,0),"No Placeholder Yet") -> IFU - Issued for Use | R45: =IFERROR(VLOOKUP(PPE_PH1_CDDL[[#This Row],[RDMC Document Number]],[3]Docs!$B:$F,5,0),"No Placeholder Yet") -> Approved | S45: =IF(AND(O45<>"",P45<>"",R45="Approved"),100%, IF(AND(O45<>"",P45<>""),66.67%, IF(O45<>"",33.33%, 0))) -> 1 | T45: IS | U45: Approved | W45: Neutral Earthing Resistor | X45: 11kV Neutral Earthing Resistor (11kV NER) | AB45: Pending
A46: 6105A | B46: K124 | C46: 0100 | D46: E | E46: DST | F46: 0005 | G46: 0 | H46: =A46&B46&"-"&C46&"-"&D46&E46&"-"&F46 -> 6105AK124-0100-EDST-0005 | I46: ="Q24050972"&"-"&"10"&"-"&C46&"-"&D46&"-"&E46&"-"&F46 -> Q24050972-10-0100-E-DST-0005 | J46: Sht 1 of 1 | K46: =VLOOKUP(C46,'PPE WBS Codes'!$E$3:$F$79,2,0) -> Project Site Wide | L46: Power Transformer | M46: 25MVA 33/11kV Dyn1 | N46: =K46&" - "&L46&" - "&M46&" - "&J46 -> Project Site Wide - Power Transformer - 25MVA 33/11kV Dyn1 - Sht 1 of 1 | O46: 45964 | P46: 45980 | Q46: =IFERROR(VLOOKUP(PPE_PH1_CDDL[[#This Row],[RDMC Document Number]],[3]Docs!$B:$F,4,0),"No Placeholder Yet") -> IFU - Issued for Use | R46: =IFERROR(VLOOKUP(PPE_PH1_CDDL[[#This Row],[RDMC Document Number]],[3]Docs!$B:$F,5,0),"No Placeholder Yet") -> Pending | S46: =IF(AND(O46<>"",P46<>"",R46="Approved"),100%, IF(AND(O46<>"",P46<>""),66.67%, IF(O46<>"",33.33%, 0))) -> 0.6667 | T46: IS | W46: Power Transformer | X46: 25MVA 33/11kV Dyn11 | AB46: Pending
A47: 6105A | B47: K124 | C47: 6262 | D47: E | E47: DST | F47: 0006 | G47: A | H47: =A47&B47&"-"&C47&"-"&D47&E47&"-"&F47 -> 6105AK124-6262-EDST-0006 | I47: ="Q24050972"&"-"&"11"&"-"&C47&"-"&D47&"-"&E47&"-"&F47 -> Q24050972-11-6262-E-DST-0006 | J47: Sht 1 of 1 | K47: =VLOOKUP(C47,'PPE WBS Codes'!$E$3:$F$79,2,0) -> Emergency Power Substation 1 and Control Room 1 | L47: Mini-substation | M47: 1MVA, Mini-substation, 11/0.69kV - Datasheet | N47: =K47&" - "&L47&" - "&M47&" - "&J47 -> Emergency Power Substation 1 and Control Room 1 - Mini-substation - 1MVA, Mini-substation, 11/0.69kV - Datasheet - Sht 1 of 1 | Q47: =IFERROR(VLOOKUP(PPE_PH1_CDDL[[#This Row],[RDMC Document Number]],[3]Docs!$B:$F,4,0),"No Placeholder Yet") -> RES - Reserved Placeholder | R47: =IFERROR(VLOOKUP(PPE_PH1_CDDL[[#This Row],[RDMC Document Number]],[3]Docs!$B:$F,5,0),"No Placeholder Yet") -> Pending | S47: =IF(AND(O47<>"",P47<>"",R47="Approved"),100%, IF(AND(O47<>"",P47<>""),66.67%, IF(O47<>"",33.33%, 0))) -> 0 | T47: IS | V47: 46157 | W47: Mini-substation | X47: Datasheet | AB47: Pending
A48: 6105A | B48: K124 | C48: 6262 | D48: E | E48: DST | F48: 0008 | G48: A | H48: =A48&B48&"-"&C48&"-"&D48&E48&"-"&F48 -> 6105AK124-6262-EDST-0008 | I48: ="Q24050972"&"-"&"11"&"-"&C48&"-"&D48&"-"&E48&"-"&F48 -> Q24050972-11-6262-E-DST-0008 | J48: Sht 1 of 1 | K48: =VLOOKUP(C48,'PPE WBS Codes'!$E$3:$F$79,2,0) -> Emergency Power Substation 1 and Control Room 1 | L48: Mini-substation | M48: 1MVA Mini-substation, 11/0.4kV - Datasheet | N48: =K48&" - "&L48&" - "&M48&" - "&J48 -> Emergency Power Substation 1 and Control Room 1 - Mini-substation - 1MVA Mini-substation, 11/0.4kV - Datasheet - Sht 1 of 1 | Q48: =IFERROR(VLOOKUP(PPE_PH1_CDDL[[#This Row],[RDMC Document Number]],[3]Docs!$B:$F,4,0),"No Placeholder Yet") -> RES - Reserved Placeholder | R48: =IFERROR(VLOOKUP(PPE_PH1_CDDL[[#This Row],[RDMC Document Number]],[3]Docs!$B:$F,5,0),"No Placeholder Yet") -> Pending | S48: =IF(AND(O48<>"",P48<>"",R48="Approved"),100%, IF(AND(O48<>"",P48<>""),66.67%, IF(O48<>"",33.33%, 0))) -> 0 | T48: IS | V48: 46157 | W48: Mini-substation | X48: 1600kVA, Mini-substation, 11/0.4kV | AB48: Pending
A49: 6105A | B49: K124 | C49: 6292 | D49: E | E49: DST | F49: 0005 | G49: A | H49: =A49&B49&"-"&C49&"-"&D49&E49&"-"&F49 -> 6105AK124-6292-EDST-0005 | I49: ="Q24050972"&"-"&"08"&"-"&C49&"-"&D49&"-"&E49&"-"&F49 -> Q24050972-08-6292-E-DST-0005 | K49: =VLOOKUP(C49,'PPE WBS Codes'!$E$3:$F$79,2,0) -> 11/33 kV Solar PV Substation 1 and Control Room 1 | L49: On-Site Power Supply & Transmission | M49: MV 33kV Solar PV Data Sheet | N49: =K49&" - "&L49&" - "&M49 -> 11/33 kV Solar PV Substation 1 and Control Room 1 - On-Site Power Supply & Transmission - MV 33kV Solar PV Data Sheet | Q49: =IFERROR(VLOOKUP(PPE_PH1_CDDL[[#This Row],[RDMC Document Number]],[3]Docs!$B:$F,4,0),"No Placeholder Yet") -> RES - Reserved Placeholder | R49: =IFERROR(VLOOKUP(PPE_PH1_CDDL[[#This Row],[RDMC Document Number]],[3]Docs!$B:$F,5,0),"No Placeholder Yet") -> Pending | S49: =IF(AND(O49<>"",P49<>"",R49="Approved"),100%, IF(AND(O49<>"",P49<>""),66.67%, IF(O49<>"",33.33%, 0))) -> 0 | T49: JC | V49: 46157 | W49: On-Site Power Supply & Transmission | X49: MV 33kV Solar PV | AB49: Pending
A50: 6105A | B50: K124 | C50: 0100 | D50: E | E50: DST | F50: 0007 | G50: A | H50: =A50&B50&"-"&C50&"-"&D50&E50&"-"&F50 -> 6105AK124-0100-EDST-0007 | I50: ="Q24050972"&"-"&"11"&"-"&C50&"-"&D50&"-"&E50&"-"&F50 -> Q24050972-11-0100-E-DST-0007 | J50: Sht 1 of 1 | K50: =VLOOKUP(C50,'PPE WBS Codes'!$E$3:$F$79,2,0) -> Project Site Wide | L50: Battery Tripping Units (BTU) | M50: Sub-Station BTU (110Vdc) | N50: =K50&" - "&L50&" - "&M50&" - "&J50 -> Project Site Wide - Battery Tripping Units (BTU) - Sub-Station BTU (110Vdc) - Sht 1 of 1 | Q50: =IFERROR(VLOOKUP(PPE_PH1_CDDL[[#This Row],[RDMC Document Number]],[3]Docs!$B:$F,4,0),"No Placeholder Yet") -> RES - Reserved Placeholder | R50: =IFERROR(VLOOKUP(PPE_PH1_CDDL[[#This Row],[RDMC Document Number]],[3]Docs!$B:$F,5,0),"No Placeholder Yet") -> Pending | S50: =IF(AND(O50<>"",P50<>"",R50="Approved"),100%, IF(AND(O50<>"",P50<>""),66.67%, IF(O50<>"",33.33%, 0))) -> 0 | T50: IS | V50: 46157 | W50: Sub-Station BTU (110Vdc) | X50: Battery Tripping Units (BTU) | AB50: Pending
A51: 6105A | B51: K124 | C51: 6262 | D51: E | E51: DST | F51: 0009 | G51: A | H51: =A51&B51&"-"&C51&"-"&D51&E51&"-"&F51 -> 6105AK124-6262-EDST-0009 | I51: =CONCATENATE(C51,,D51,"-",E51,"-",F51,G51,"-",H51) -> 6262E-DST-0009A-6105AK124-6262-EDST-0009 | J51: Sht 1 of 1 | K51: =VLOOKUP(C51,'PPE WBS Codes'!$E$3:$F$79,2,0) -> Emergency Power Substation 1 and Control Room 1 | L51: Neutral Earthing Resistor | M51: 690V NER (300A) | N51: =K51&" - "&L51&" - "&M51&" - "&J51 -> Emergency Power Substation 1 and Control Room 1 - Neutral Earthing Resistor - 690V NER (300A) - Sht 1 of 1 | Q51: =IFERROR(VLOOKUP(PPE_PH1_CDDL[[#This Row],[RDMC Document Number]],[3]Docs!$B:$F,4,0),"No Placeholder Yet") -> RES - Reserved Placeholder | R51: =IFERROR(VLOOKUP(PPE_PH1_CDDL[[#This Row],[RDMC Document Number]],[3]Docs!$B:$F,5,0),"No Placeholder Yet") -> Pending | S51: =IF(AND(O51<>"",P51<>"",R51="Approved"),100%, IF(AND(O51<>"",P51<>""),66.67%, IF(O51<>"",33.33%, 0))) -> 0 | T51: IS | V51: 46157 | W51: Neutral Earthing Resistor | X51: 690V NER (300A) | AB51: Pending
A52: 6105A | B52: K124 | C52: 6286 | D52: E | E52: DST | F52: 0006 | G52: A | H52: =A52&B52&"-"&C52&"-"&D52&E52&"-"&F52 -> 6105AK124-6286-EDST-0006 | I52: ="Q24050972"&"-"&"07"&"-"&C52&"-"&D52&"-"&E52&"-"&F52 -> Q24050972-07-6286-E-DST-0006 | J52: Sht 1 of 1 | K52: =VLOOKUP(C52,'PPE WBS Codes'!$E$3:$F$79,2,0) -> Primary Crushing | L52: Auxiliary Supply | M52: 250kVA, Mini-substation, 11/0.4kV - Datasheet | N52: =K52&" - "&L52&" - "&M52&" - "&J52 -> Primary Crushing - Auxiliary Supply - 250kVA, Mini-substation, 11/0.4kV - Datasheet - Sht 1 of 1 | Q52: =IFERROR(VLOOKUP(PPE_PH1_CDDL[[#This Row],[RDMC Document Number]],[3]Docs!$B:$F,4,0),"No Placeholder Yet") -> RES - Reserved Placeholder | R52: =IFERROR(VLOOKUP(PPE_PH1_CDDL[[#This Row],[RDMC Document Number]],[3]Docs!$B:$F,5,0),"No Placeholder Yet") -> Pending | S52: =IF(AND(N52<>"",O52<>"",R52="Approved"),100%, IF(AND(N52<>"",O52<>""),66.67%, IF(N52<>"",33.33%, 0))) -> 0.3333 | T52: IS | V52: 46157 | W52: Auxiliary Supply | X52: 250kVA, Mini-substation, 11/0.4kV | AB52: Pending
A53: 6105A | B53: K124 | C53: 0100 | D53: E | E53: DST | F53: 0008 | G53: A | H53: =A53&B53&"-"&C53&"-"&D53&E53&"-"&F53 -> 6105AK124-0100-EDST-0008 | I53: ="Q24050972"&"-"&"12"&"-"&C53&"-"&D53&"-"&E53&"-"&F53 -> Q24050972-12-0100-E-DST-0008 | J53: Sht 1 of 1 | K53: =VLOOKUP(C53,'PPE WBS Codes'!$E$3:$F$79,2,0) -> Project Site Wide | L53: Auxiliary Supply | M53: 250kVA Mini-substation, 33/0.4kV - Datasheet | N53: =K53&" - "&L53&" - "&M53&" - "&J53 -> Project Site Wide - Auxiliary Supply - 250kVA Mini-substation, 33/0.4kV - Datasheet - Sht 1 of 1 | Q53: =IFERROR(VLOOKUP(PPE_PH1_CDDL[[#This Row],[RDMC Document Number]],[3]Docs!$B:$F,4,0),"No Placeholder Yet") -> RES - Reserved Placeholder | R53: =IFERROR(VLOOKUP(PPE_PH1_CDDL[[#This Row],[RDMC Document Number]],[3]Docs!$B:$F,5,0),"No Placeholder Yet") -> Pending | S53: =IF(AND(O53<>"",P53<>"",R53="Approved"),100%, IF(AND(O53<>"",P53<>""),66.67%, IF(O53<>"",33.33%, 0))) -> 0 | T53: IS | V53: 46157 | W53: Auxiliary Supply | X53: 400kVA, Mini-substation | AB53: Pending
A54: 6105A | B54: K124 | C54: 0100 | D54: E | E54: DST | F54: 0009 | G54: 0 | H54: =A54&B54&"-"&C54&"-"&D54&E54&"-"&F54 -> 6105AK124-0100-EDST-0009 | I54: ="Q24050972"&"-"&"12"&"-"&C54&"-"&D54&"-"&E54&"-"&F54 -> Q24050972-12-0100-E-DST-0009 | J54: Sht 1 of 1 | K54: =VLOOKUP(C54,'PPE WBS Codes'!$E$3:$F$79,2,0) -> Project Site Wide | L54: Insulation Monitoring & High Impedance Earthing | M54: IM-Flex - 690Vac - General Arrangement | N54: =K54&" - "&L54&" - "&M54&" - "&J54 -> Project Site Wide - Insulation Monitoring & High Impedance Earthing - IM-Flex - 690Vac - General Arrangement - Sht 1 of 1 | O54: 46006 | P54: 46043 | Q54: =IFERROR(VLOOKUP(PPE_PH1_CDDL[[#This Row],[RDMC Document Number]],[3]Docs!$B:$F,4,0),"No Placeholder Yet") -> IFC - Issued for Construction | R54: =IFERROR(VLOOKUP(PPE_PH1_CDDL[[#This Row],[RDMC Document Number]],[3]Docs!$B:$F,5,0),"No Placeholder Yet") -> Approved | S54: =IF(AND(O54<>"",P54<>"",R54="Approved"),100%, IF(AND(O54<>"",P54<>""),66.67%, IF(O54<>"",33.33%, 0))) -> 1 | T54: IS | U54: Approved | W54: Insulation Monitoring | X54: General Arrangement | AB54: Pending
A55: 6105A | B55: K124 | C55: 0100 | D55: E | E55: DST | F55: 0010 | G55: 0 | H55: =A55&B55&"-"&C55&"-"&D55&E55&"-"&F55 -> 6105AK124-0100-EDST-0010 | I55: ="Q24050972"&"-"&"12"&"-"&C55&"-"&D55&"-"&E55&"-"&F55 -> Q24050972-12-0100-E-DST-0010 | J55: Sht 1 of 2 | K55: =VLOOKUP(C55,'PPE WBS Codes'!$E$3:$F$79,2,0) -> Project Site Wide | L55: Insulation Monitoring & High Impedance Earthing | M55: IM-Flex - 690Vac - Circuit Diagram | N55: =K55&" - "&L55&" - "&M55&" - "&J55 -> Project Site Wide - Insulation Monitoring & High Impedance Earthing - IM-Flex - 690Vac - Circuit Diagram - Sht 1 of 2 | O55: 46006 | P55: 46043 | Q55: =IFERROR(VLOOKUP(PPE_PH1_CDDL[[#This Row],[RDMC Document Number]],[3]Docs!$B:$F,4,0),"No Placeholder Yet") -> IFC - Issued for Construction | R55: =IFERROR(VLOOKUP(PPE_PH1_CDDL[[#This Row],[RDMC Document Number]],[3]Docs!$B:$F,5,0),"No Placeholder Yet") -> Approved | S55: =IF(AND(O55<>"",P55<>"",R55="Approved"),100%, IF(AND(O55<>"",P55<>""),66.67%, IF(O55<>"",33.33%, 0))) -> 1 | T55: IS | U55: Approved | W55: Insulation Monitoring | X55: Circuit Diagram | AB55: Pending
A56: 6105A | B56: K124 | C56: 0100 | D56: E | E56: DST | F56: 0011 | G56: 0 | H56: =A56&B56&"-"&C56&"-"&D56&E56&"-"&F56 -> 6105AK124-0100-EDST-0011 | I56: ="Q24050972"&"-"&"12"&"-"&C56&"-"&D56&"-"&E56&"-"&F56 -> Q24050972-12-0100-E-DST-0011 | J56: Sht 2 of 2 | K56: =VLOOKUP(C56,'PPE WBS Codes'!$E$3:$F$79,2,0) -> Project Site Wide | L56: Insulation Monitoring & High Impedance Earthing | M56: IM-Flex - 690Vac - Circuit Diagram | N56: =K56&" - "&L56&" - "&M56&" - "&J56 -> Project Site Wide - Insulation Monitoring & High Impedance Earthing - IM-Flex - 690Vac - Circuit Diagram - Sht 2 of 2 | O56: 46006 | P56: 46162 | Q56: =IFERROR(VLOOKUP(PPE_PH1_CDDL[[#This Row],[RDMC Document Number]],[3]Docs!$B:$F,4,0),"No Placeholder Yet") -> IFC - Issued for Construction | R56: =IFERROR(VLOOKUP(PPE_PH1_CDDL[[#This Row],[RDMC Document Number]],[3]Docs!$B:$F,5,0),"No Placeholder Yet") -> Rejected - Revise & Resubmit | S56: =IF(AND(O56<>"",P56<>"",R56="Approved"),100%, IF(AND(O56<>"",P56<>""),66.67%, IF(O56<>"",33.33%, 0))) -> 0.6667 | T56: IS | W56: Insulation Monitoring | X56: Circuit Diagram | AB56: Pending
A57: 6105A | B57: K124 | C57: 6262 | D57: E | E57: DST | F57: 0010 | G57: A | H57: =A57&B57&"-"&C57&"-"&D57&E57&"-"&F57 -> 6105AK124-6262-EDST-0010 | I57: ="Q24050972"&"-"&"12"&"-"&C57&"-"&D57&"-"&E57&"-"&F57 -> Q24050972-12-6262-E-DST-0010 | K57: =VLOOKUP(C57,'PPE WBS Codes'!$E$3:$F$79,2,0) -> Emergency Power Substation 1 and Control Room 1 | L57: High Impedance Earthing | M57: Datasheet | N57: =K57&" - "&L57&" - "&M57 -> Emergency Power Substation 1 and Control Room 1 - High Impedance Earthing - Datasheet | Q57: =IFERROR(VLOOKUP(PPE_PH1_CDDL[[#This Row],[RDMC Document Number]],[3]Docs!$B:$F,4,0),"No Placeholder Yet") -> RES - Reserved Placeholder | R57: =IFERROR(VLOOKUP(PPE_PH1_CDDL[[#This Row],[RDMC Document Number]],[3]Docs!$B:$F,5,0),"No Placeholder Yet") -> Pending | S57: =IF(AND(O57<>"",P57<>"",R57="Approved"),100%, IF(AND(O57<>"",P57<>""),66.67%, IF(O57<>"",33.33%, 0))) -> 0 | T57: RS | V57: 46203 | W57: Earthing | X57: Datasheet | AB57: Pending
A58: 6105A | B58: K124 | C58: 6282 | D58: E | E58: DST | F58: 0001 | G58: A | H58: =A58&B58&"-"&C58&"-"&D58&E58&"-"&F58 -> 6105AK124-6282-EDST-0001 | I58: ="Q24050972"&"-"&"01"&"-"&C58&"-"&D58&"-"&E58&"-"&F58 -> Q24050972-01-6282-E-DST-0001 | J58: Sht 1 of 1 | K58: =VLOOKUP(C58,'PPE WBS Codes'!$E$3:$F$79,2,0) -> Potable Water Treatment Plant | L58: Pole Mounted Transformer | M58: 500kVA, 33/0.69kV | N58: =K58&" - "&L58&" - "&M58 -> Potable Water Treatment Plant - Pole Mounted Transformer - 500kVA, 33/0.69kV | Q58: =IFERROR(VLOOKUP(PPE_PH1_CDDL[[#This Row],[RDMC Document Number]],[3]Docs!$B:$F,4,0),"No Placeholder Yet") -> RES - Reserved Placeholder | R58: =IFERROR(VLOOKUP(PPE_PH1_CDDL[[#This Row],[RDMC Document Number]],[3]Docs!$B:$F,5,0),"No Placeholder Yet") -> Pending | S58: =IF(AND(O58<>"",P58<>"",R58="Approved"),100%, IF(AND(O58<>"",P58<>""),66.67%, IF(O58<>"",33.33%, 0))) -> 0 | T58: RS | V58: 46203 | W58: Mini-substation | X58: Datasheet | AB58: Pending
A59: 6105A | B59: K124 | C59: 6286 | D59: E | E59: DTL | F59: 0001 | G59: A | H59: =A59&B59&"-"&C59&"-"&D59&E59&"-"&F59 -> 6105AK124-6286-EDTL-0001 | I59: ="Q24050972"&"-"&"07"&"-"&C59&"-"&D59&"-"&E59&"-"&F59 -> Q24050972-07-6286-E-DTL-0001 | J59: Sht 3 of 3 | K59: =VLOOKUP(C59,'PPE WBS Codes'!$E$3:$F$79,2,0) -> Primary Crushing | L59: Auxiliary 400V AC Panel 2 | M59: Details | N59: =K59&" - "&L59&" - "&M59&" - "&J59 -> Primary Crushing - Auxiliary 400V AC Panel 2 - Details - Sht 3 of 3 | Q59: =IFERROR(VLOOKUP(PPE_PH1_CDDL[[#This Row],[RDMC Document Number]],[3]Docs!$B:$F,4,0),"No Placeholder Yet") -> RES - Reserved Placeholder | R59: =IFERROR(VLOOKUP(PPE_PH1_CDDL[[#This Row],[RDMC Document Number]],[3]Docs!$B:$F,5,0),"No Placeholder Yet") -> Pending | S59: =IF(AND(O59<>"",P59<>"",R59="Approved"),100%, IF(AND(O59<>"",P59<>""),66.67%, IF(O59<>"",33.33%, 0))) -> 0 | T59: IS | V59: TENDER | W59: Auxiliary 400V AC Panel 2 | X59: Details | AB59: Pending
A60: 6105A | B60: K124 | C60: 6286 | D60: E | E60: DTL | F60: 0002 | G60: A | H60: =A60&B60&"-"&C60&"-"&D60&E60&"-"&F60 -> 6105AK124-6286-EDTL-0002 | I60: ="Q24050972"&"-"&"07"&"-"&C60&"-"&D60&"-"&E60&"-"&F60 -> Q24050972-07-6286-E-DTL-0002 | J60: Sht 2 of 3 | K60: =VLOOKUP(C60,'PPE WBS Codes'!$E$3:$F$79,2,0) -> Primary Crushing | L60: Auxiliary 400V AC Panel 2 | M60: Details | N60: =K60&" - "&L60&" - "&M60&" - "&J60 -> Primary Crushing - Auxiliary 400V AC Panel 2 - Details - Sht 2 of 3 | Q60: =IFERROR(VLOOKUP(PPE_PH1_CDDL[[#This Row],[RDMC Document Number]],[3]Docs!$B:$F,4,0),"No Placeholder Yet") -> RES - Reserved Placeholder | R60: =IFERROR(VLOOKUP(PPE_PH1_CDDL[[#This Row],[RDMC Document Number]],[3]Docs!$B:$F,5,0),"No Placeholder Yet") -> Pending | S60: =IF(AND(O60<>"",P60<>"",R60="Approved"),100%, IF(AND(O60<>"",P60<>""),66.67%, IF(O60<>"",33.33%, 0))) -> 0 | T60: IS | V60: TENDER | W60: Auxiliary 400V AC Panel 2 | X60: Details | AB60: Pending
A61: 6105A | B61: K124 | C61: 6260 | D61: E | E61: DTL | F61: 0001 | G61: A | H61: =A61&B61&"-"&C61&"-"&D61&E61&"-"&F61 -> 6105AK124-6260-EDTL-0001 | I61: ="Q24050972"&"-"&"09"&"-"&C61&"-"&D61&"-"&E61&"-"&F61 -> Q24050972-09-6260-E-DTL-0001 | J61: Sht.4 of 4 | K61: =VLOOKUP(C61,'PPE WBS Codes'!$E$3:$F$79,2,0) -> Emergency Power Generation (Main Plant) | L61: Mv Cable Isolator Panel | M61: Details | N61: =K61&" - "&L61&" - "&M61&" - "&J61 -> Emergency Power Generation (Main Plant) - Mv Cable Isolator Panel - Details - Sht.4 of 4 | Q61: =IFERROR(VLOOKUP(PPE_PH1_CDDL[[#This Row],[RDMC Document Number]],[3]Docs!$B:$F,4,0),"No Placeholder Yet") -> RES - Reserved Placeholder | R61: =IFERROR(VLOOKUP(PPE_PH1_CDDL[[#This Row],[RDMC Document Number]],[3]Docs!$B:$F,5,0),"No Placeholder Yet") -> Pending | S61: =IF(AND(O61<>"",P61<>"",R61="Approved"),100%, IF(AND(O61<>"",P61<>""),66.67%, IF(O61<>"",33.33%, 0))) -> 0 | T61: CLR | V61: TENDER | W61: Mv Cable Isolator Panel | X61: Details | AB61: Pending
A62: 6105A | B62: K124 | C62: 0100 | D62: H | E62: FRM | F62: 0001 | G62: A | H62: =A62&B62&"-"&C62&"-"&D62&E62&"-"&F62 -> 6105AK124-0100-HFRM-0001 | I62: ="Q24050972"&"-"&"09"&"-"&C62&"-"&D62&"-"&E62&"-"&F62 -> Q24050972-09-0100-H-FRM-0001 | K62: =VLOOKUP(C62,'PPE WBS Codes'!$E$3:$F$79,2,0) -> Project Site Wide | L62: Daily Safety Task Instruction DSTI | M62: Form | N62: =K62&" - "&L62&" - "&M62 -> Project Site Wide - Daily Safety Task Instruction DSTI - Form | Q62: =IFERROR(VLOOKUP(PPE_PH1_CDDL[[#This Row],[RDMC Document Number]],[3]Docs!$B:$F,4,0),"No Placeholder Yet") -> RES - Reserved Placeholder | R62: =IFERROR(VLOOKUP(PPE_PH1_CDDL[[#This Row],[RDMC Document Number]],[3]Docs!$B:$F,5,0),"No Placeholder Yet") -> Pending | S62: =IF(AND(O62<>"",P62<>"",R62="Approved"),100%, IF(AND(O62<>"",P62<>""),66.67%, IF(O62<>"",33.33%, 0))) -> 0 | T62: FV | V62: 46188 | W62: Daily Safety Task Instruction DSTI | X62: Form | AB62: Pending
A63: 6105A | B63: K124 | C63: 0100 | D63: H | E63: FRM | F63: 0002 | G63: A | H63: =A63&B63&"-"&C63&"-"&D63&E63&"-"&F63 -> 6105AK124-0100-HFRM-0002 | I63: ="Q24050972"&"-"&"09"&"-"&C63&"-"&D63&"-"&E63&"-"&F63 -> Q24050972-09-0100-H-FRM-0002 | K63: =VLOOKUP(C63,'PPE WBS Codes'!$E$3:$F$79,2,0) -> Project Site Wide | L63: SHE Risk Assessment Blank | M63: Form | N63: =K63&" - "&L63&" - "&M63 -> Project Site Wide - SHE Risk Assessment Blank - Form | Q63: =IFERROR(VLOOKUP(PPE_PH1_CDDL[[#This Row],[RDMC Document Number]],[3]Docs!$B:$F,4,0),"No Placeholder Yet") -> RES - Reserved Placeholder | R63: =IFERROR(VLOOKUP(PPE_PH1_CDDL[[#This Row],[RDMC Document Number]],[3]Docs!$B:$F,5,0),"No Placeholder Yet") -> Pending | S63: =IF(AND(O63<>"",P63<>"",R63="Approved"),100%, IF(AND(O63<>"",P63<>""),66.67%, IF(O63<>"",33.33%, 0))) -> 0 | T63: FV | V63: 46188 | W63: SHE Risk Assessment Blank | X63: Form | AB63: Pending
A64: 6105A | B64: K124 | C64: 0100 | D64: H | E64: FRM | F64: 0003 | G64: A | H64: =A64&B64&"-"&C64&"-"&D64&E64&"-"&F64 -> 6105AK124-0100-HFRM-0003 | I64: ="Q24050972"&"-"&"09"&"-"&C64&"-"&D64&"-"&E64&"-"&F64 -> Q24050972-09-0100-H-FRM-0003 | K64: =VLOOKUP(C64,'PPE WBS Codes'!$E$3:$F$79,2,0) -> Project Site Wide | L64: Noise SHE Risk Assessment | M64: Form | N64: =K64&" - "&L64&" - "&M64 -> Project Site Wide - Noise SHE Risk Assessment - Form | Q64: =IFERROR(VLOOKUP(PPE_PH1_CDDL[[#This Row],[RDMC Document Number]],[3]Docs!$B:$F,4,0),"No Placeholder Yet") -> RES - Reserved Placeholder | R64: =IFERROR(VLOOKUP(PPE_PH1_CDDL[[#This Row],[RDMC Document Number]],[3]Docs!$B:$F,5,0),"No Placeholder Yet") -> Pending | S64: =IF(AND(O64<>"",P64<>"",R64="Approved"),100%, IF(AND(O64<>"",P64<>""),66.67%, IF(O64<>"",33.33%, 0))) -> 0 | T64: FV | V64: 46188 | W64: Noise SHE Risk Assessment | X64: Form | AB64: Pending
A65: 6105A | B65: K124 | C65: 0100 | D65: H | E65: FRM | F65: 0004 | G65: A | H65: =A65&B65&"-"&C65&"-"&D65&E65&"-"&F65 -> 6105AK124-0100-HFRM-0004 | I65: ="Q24050972"&"-"&"09"&"-"&C65&"-"&D65&"-"&E65&"-"&F65 -> Q24050972-09-0100-H-FRM-0004 | K65: =VLOOKUP(C65,'PPE WBS Codes'!$E$3:$F$79,2,0) -> Project Site Wide | L65: Risk Assessment for First Aid Provision | M65: Form | N65: =K65&" - "&L65&" - "&M65 -> Project Site Wide - Risk Assessment for First Aid Provision - Form | Q65: =IFERROR(VLOOKUP(PPE_PH1_CDDL[[#This Row],[RDMC Document Number]],[3]Docs!$B:$F,4,0),"No Placeholder Yet") -> RES - Reserved Placeholder | R65: =IFERROR(VLOOKUP(PPE_PH1_CDDL[[#This Row],[RDMC Document Number]],[3]Docs!$B:$F,5,0),"No Placeholder Yet") -> Pending | S65: =IF(AND(O65<>"",P65<>"",R65="Approved"),100%, IF(AND(O65<>"",P65<>""),66.67%, IF(O65<>"",33.33%, 0))) -> 0 | T65: FV | V65: 46188 | W65: Risk Assessment for First Aid Provision | X65: Form | AB65: Pending
A66: 6105A | B66: K124 | C66: 0100 | D66: H | E66: FRM | F66: 0005 | G66: A | H66: =A66&B66&"-"&C66&"-"&D66&E66&"-"&F66 -> 6105AK124-0100-HFRM-0005 | I66: ="Q24050972"&"-"&"09"&"-"&C66&"-"&D66&"-"&E66&"-"&F66 -> Q24050972-09-0100-H-FRM-0005 | K66: =VLOOKUP(C66,'PPE WBS Codes'!$E$3:$F$79,2,0) -> Project Site Wide | L66: Work in Extreme Hot Conditions SHE Risk Assessment | M66: Form | N66: =K66&" - "&L66&" - "&M66 -> Project Site Wide - Work in Extreme Hot Conditions SHE Risk Assessment - Form | Q66: =IFERROR(VLOOKUP(PPE_PH1_CDDL[[#This Row],[RDMC Document Number]],[3]Docs!$B:$F,4,0),"No Placeholder Yet") -> RES - Reserved Placeholder | R66: =IFERROR(VLOOKUP(PPE_PH1_CDDL[[#This Row],[RDMC Document Number]],[3]Docs!$B:$F,5,0),"No Placeholder Yet") -> Pending | S66: =IF(AND(O66<>"",P66<>"",R66="Approved"),100%, IF(AND(O66<>"",P66<>""),66.67%, IF(O66<>"",33.33%, 0))) -> 0 | T66: FV | V66: 46188 | W66: Work in Extreme Hot Conditions SHE Risk Assessment | X66: Form | AB66: Pending
A67: 6105A | B67: K124 | C67: 0100 | D67: H | E67: FRM | F67: 0006 | G67: A | H67: =A67&B67&"-"&C67&"-"&D67&E67&"-"&F67 -> 6105AK124-0100-HFRM-0006 | I67: ="Q24050972"&"-"&"09"&"-"&C67&"-"&D67&"-"&E67&"-"&F67 -> Q24050972-09-0100-H-FRM-0006 | K67: =VLOOKUP(C67,'PPE WBS Codes'!$E$3:$F$79,2,0) -> Project Site Wide | L67: Personal Protective Equipment SHE Risk Assessment | M67: Form | N67: =K67&" - "&L67&" - "&M67 -> Project Site Wide - Personal Protective Equipment SHE Risk Assessment - Form | Q67: =IFERROR(VLOOKUP(PPE_PH1_CDDL[[#This Row],[RDMC Document Number]],[3]Docs!$B:$F,4,0),"No Placeholder Yet") -> RES - Reserved Placeholder | R67: =IFERROR(VLOOKUP(PPE_PH1_CDDL[[#This Row],[RDMC Document Number]],[3]Docs!$B:$F,5,0),"No Placeholder Yet") -> Pending | S67: =IF(AND(O67<>"",P67<>"",R67="Approved"),100%, IF(AND(O67<>"",P67<>""),66.67%, IF(O67<>"",33.33%, 0))) -> 0 | T67: FV | V67: 46188 | W67: Personal Protective Equipment SHE Risk Assessment | X67: Form | AB67: Pending
A68: 6105A | B68: K124 | C68: 0100 | D68: H | E68: FRM | F68: 0007 | G68: A | H68: =A68&B68&"-"&C68&"-"&D68&E68&"-"&F68 -> 6105AK124-0100-HFRM-0007 | I68: ="Q24050972"&"-"&"09"&"-"&C68&"-"&D68&"-"&E68&"-"&F68 -> Q24050972-09-0100-H-FRM-0007 | K68: =VLOOKUP(C68,'PPE WBS Codes'!$E$3:$F$79,2,0) -> Project Site Wide | L68: Display Screen Equipment DSE SHE Risk Assessment | M68: Form | N68: =K68&" - "&L68&" - "&M68 -> Project Site Wide - Display Screen Equipment DSE SHE Risk Assessment - Form | Q68: =IFERROR(VLOOKUP(PPE_PH1_CDDL[[#This Row],[RDMC Document Number]],[3]Docs!$B:$F,4,0),"No Placeholder Yet") -> RES - Reserved Placeholder | R68: =IFERROR(VLOOKUP(PPE_PH1_CDDL[[#This Row],[RDMC Document Number]],[3]Docs!$B:$F,5,0),"No Placeholder Yet") -> Pending | S68: =IF(AND(O68<>"",P68<>"",R68="Approved"),100%, IF(AND(O68<>"",P68<>""),66.67%, IF(O68<>"",33.33%, 0))) -> 0 | T68: FV | V68: 46188 | W68: Display Screen Equipment DSE SHE Risk Assessment | X68: Form | AB68: Pending
A69: 6105A | B69: K124 | C69: 0100 | D69: H | E69: FRM | F69: 0008 | G69: A | H69: =A69&B69&"-"&C69&"-"&D69&E69&"-"&F69 -> 6105AK124-0100-HFRM-0008 | I69: ="Q24050972"&"-"&"09"&"-"&C69&"-"&D69&"-"&E69&"-"&F69 -> Q24050972-09-0100-H-FRM-0008 | K69: =VLOOKUP(C69,'PPE WBS Codes'!$E$3:$F$79,2,0) -> Project Site Wide | L69: Hand Tools SHE Risk Assessment | M69: Form | N69: =K69&" - "&L69&" - "&M69 -> Project Site Wide - Hand Tools SHE Risk Assessment - Form | Q69: =IFERROR(VLOOKUP(PPE_PH1_CDDL[[#This Row],[RDMC Document Number]],[3]Docs!$B:$F,4,0),"No Placeholder Yet") -> RES - Reserved Placeholder | R69: =IFERROR(VLOOKUP(PPE_PH1_CDDL[[#This Row],[RDMC Document Number]],[3]Docs!$B:$F,5,0),"No Placeholder Yet") -> Pending | S69: =IF(AND(O69<>"",P69<>"",R69="Approved"),100%, IF(AND(O69<>"",P69<>""),66.67%, IF(O69<>"",33.33%, 0))) -> 0 | T69: FV | V69: 46188 | W69: Hand Tools SHE Risk Assessment | X69: Form | AB69: Pending
A70: 6105A | B70: K124 | C70: 0100 | D70: H | E70: FRM | F70: 0009 | G70: A | H70: =A70&B70&"-"&C70&"-"&D70&E70&"-"&F70 -> 6105AK124-0100-HFRM-0009 | I70: ="Q24050972"&"-"&"09"&"-"&C70&"-"&D70&"-"&E70&"-"&F70 -> Q24050972-09-0100-H-FRM-0009 | K70: =VLOOKUP(C70,'PPE WBS Codes'!$E$3:$F$79,2,0) -> Project Site Wide | L70: Legionnaires Disease SHE Risk Assessment | M70: Form | N70: =K70&" - "&L70&" - "&M70 -> Project Site Wide - Legionnaires Disease SHE Risk Assessment - Form | Q70: =IFERROR(VLOOKUP(PPE_PH1_CDDL[[#This Row],[RDMC Document Number]],[3]Docs!$B:$F,4,0),"No Placeholder Yet") -> RES - Reserved Placeholder | R70: =IFERROR(VLOOKUP(PPE_PH1_CDDL[[#This Row],[RDMC Document Number]],[3]Docs!$B:$F,5,0),"No Placeholder Yet") -> Pending | S70: =IF(AND(O70<>"",P70<>"",R70="Approved"),100%, IF(AND(O70<>"",P70<>""),66.67%, IF(O70<>"",33.33%, 0))) -> 0 | T70: FV | V70: 46188 | W70: Legionnaires Disease SHE Risk Assessment | X70: Form | AB70: Pending
A71: 6105A | B71: K124 | C71: 0100 | D71: H | E71: FRM | F71: 0010 | G71: A | H71: =A71&B71&"-"&C71&"-"&D71&E71&"-"&F71 -> 6105AK124-0100-HFRM-0010 | I71: ="Q24050972"&"-"&"09"&"-"&C71&"-"&D71&"-"&E71&"-"&F71 -> Q24050972-09-0100-H-FRM-0010 | K71: =VLOOKUP(C71,'PPE WBS Codes'!$E$3:$F$79,2,0) -> Project Site Wide | L71: Working at Height SHE Risk Assessment | M71: Form | N71: =K71&" - "&L71&" - "&M71 -> Project Site Wide - Working at Height SHE Risk Assessment - Form | Q71: =IFERROR(VLOOKUP(PPE_PH1_CDDL[[#This Row],[RDMC Document Number]],[3]Docs!$B:$F,4,0),"No Placeholder Yet") -> RES - Reserved Placeholder | R71: =IFERROR(VLOOKUP(PPE_PH1_CDDL[[#This Row],[RDMC Document Number]],[3]Docs!$B:$F,5,0),"No Placeholder Yet") -> Pending | S71: =IF(AND(O71<>"",P71<>"",R71="Approved"),100%, IF(AND(O71<>"",P71<>""),66.67%, IF(O71<>"",33.33%, 0))) -> 0 | T71: FV | V71: 46188 | W71: Working at Height SHE Risk Assessment | X71: Form | AB71: Pending
A72: 6105A | B72: K124 | C72: 0100 | D72: H | E72: FRM | F72: 0011 | G72: A | H72: =A72&B72&"-"&C72&"-"&D72&E72&"-"&F72 -> 6105AK124-0100-HFRM-0011 | I72: ="Q24050972"&"-"&"09"&"-"&C72&"-"&D72&"-"&E72&"-"&F72 -> Q24050972-09-0100-H-FRM-0011 | K72: =VLOOKUP(C72,'PPE WBS Codes'!$E$3:$F$79,2,0) -> Project Site Wide | L72: Driving SHE Risk Assessment | M72: Form | N72: =K72&" - "&L72&" - "&M72 -> Project Site Wide - Driving SHE Risk Assessment - Form | Q72: =IFERROR(VLOOKUP(PPE_PH1_CDDL[[#This Row],[RDMC Document Number]],[3]Docs!$B:$F,4,0),"No Placeholder Yet") -> RES - Reserved Placeholder | R72: =IFERROR(VLOOKUP(PPE_PH1_CDDL[[#This Row],[RDMC Document Number]],[3]Docs!$B:$F,5,0),"No Placeholder Yet") -> Pending | S72: =IF(AND(O72<>"",P72<>"",R72="Approved"),100%, IF(AND(O72<>"",P72<>""),66.67%, IF(O72<>"",33.33%, 0))) -> 0 | T72: FV | V72: 46188 | W72: Driving SHE Risk Assessment | X72: Form | AB72: Pending
A73: 6105A | B73: K124 | C73: 0100 | D73: H | E73: FRM | F73: 0012 | G73: A | H73: =A73&B73&"-"&C73&"-"&D73&E73&"-"&F73 -> 6105AK124-0100-HFRM-0012 | I73: ="Q24050972"&"-"&"09"&"-"&C73&"-"&D73&"-"&E73&"-"&F73 -> Q24050972-09-0100-H-FRM-0012 | K73: =VLOOKUP(C73,'PPE WBS Codes'!$E$3:$F$79,2,0) -> Project Site Wide | L73: Access on Working Scaffolds SHE Risk Assessment | M73: Form | N73: =K73&" - "&L73&" - "&M73 -> Project Site Wide - Access on Working Scaffolds SHE Risk Assessment - Form | Q73: =IFERROR(VLOOKUP(PPE_PH1_CDDL[[#This Row],[RDMC Document Number]],[3]Docs!$B:$F,4,0),"No Placeholder Yet") -> RES - Reserved Placeholder | R73: =IFERROR(VLOOKUP(PPE_PH1_CDDL[[#This Row],[RDMC Document Number]],[3]Docs!$B:$F,5,0),"No Placeholder Yet") -> Pending | S73: =IF(AND(O73<>"",P73<>"",R73="Approved"),100%, IF(AND(O73<>"",P73<>""),66.67%, IF(O73<>"",33.33%, 0))) -> 0 | T73: FV | V73: 46188 | W73: Access on Working Scaffolds SHE Risk Assessment | X73: Form | AB73: Pending
... A91: 6105A | B91: K124 | C91: 0100 | D91: H | E91: FRM | F91: 0030 | G91: A | H91: =A91&B91&"-"&C91&"-"&D91&E91&"-"&F91 -> 6105AK124-0100-HFRM-0030 | I91: ="Q24050972"&"-"&"09"&"-"&C91&"-"&D91&"-"&E91&"-"&F91 -> Q24050972-09-0100-H-FRM-0030 | K91: =VLOOKUP(C91,'PPE WBS Codes'!$E$3:$F$79,2,0) -> Project Site Wide | L91: Two-Week-Lookahead | M91: Form | N91: =K91&" - "&L91&" - "&M91 -> Project Site Wide - Two-Week-Lookahead - Form | Q91: =IFERROR(VLOOKUP(PPE_PH1_CDDL[[#This Row],[RDMC Document Number]],[3]Docs!$B:$F,4,0),"No Placeholder Yet") -> RES - Reserved Placeholder | R91: =IFERROR(VLOOKUP(PPE_PH1_CDDL[[#This Row],[RDMC Document Number]],[3]Docs!$B:$F,5,0),"No Placeholder Yet") -> Pending | S91: =IF(AND(O91<>"",P91<>"",R91="Approved"),100%, IF(AND(O91<>"",P91<>""),66.67%, IF(O91<>"",33.33%, 0))) -> 0 | T91: FV | V91: 46188 | W91: Two-Week-Lookahead | X91: Form | AB91: Pending
A92: 6105A | B92: K124 | C92: 6260 | D92: E | E92: GAD | F92: 0002 | G92: A | H92: =A92&B92&"-"&C92&"-"&D92&E92&"-"&F92 -> 6105AK124-6260-EGAD-0002 | I92: ="Q24050972"&"-"&"04"&"-"&C92&"-"&D92&"-"&E92&"-"&F92 -> Q24050972-04-6260-E-GAD-0002 | J92: Sht 1 of 1 | K92: =VLOOKUP(C92,'PPE WBS Codes'!$E$3:$F$79,2,0) -> Emergency Power Generation (Main Plant) | L92: MV Switch Board | M92: General Arrangement | N92: =K92&" - "&L92&" - "&M92&" - "&J92 -> Emergency Power Generation (Main Plant) - MV Switch Board - General Arrangement - Sht 1 of 1 | Q92: =IFERROR(VLOOKUP(PPE_PH1_CDDL[[#This Row],[RDMC Document Number]],[3]Docs!$B:$F,4,0),"No Placeholder Yet") -> RES - Reserved Placeholder | R92: =IFERROR(VLOOKUP(PPE_PH1_CDDL[[#This Row],[RDMC Document Number]],[3]Docs!$B:$F,5,0),"No Placeholder Yet") -> Pending | S92: =IF(AND(O92<>"",P92<>"",R92="Approved"),100%, IF(AND(O92<>"",P92<>""),66.67%, IF(O92<>"",33.33%, 0))) -> 0 | T92: IS | V92: TENDER | W92: MV Switch Board | X92: General Arrangement | AB92: Pending
A93: 6105A | B93: K124 | C93: 6260 | D93: E | E93: GAD | F93: 0005 | G93: A | H93: =A93&B93&"-"&C93&"-"&D93&E93&"-"&F93 -> 6105AK124-6260-EGAD-0005 | I93: ="Q24050972"&"-"&"07"&"-"&C93&"-"&D93&"-"&E93&"-"&F93 -> Q24050972-07-6260-E-GAD-0005 | J93: Sht 1 of 8 | K93: =VLOOKUP(C93,'PPE WBS Codes'!$E$3:$F$79,2,0) -> Emergency Power Generation (Main Plant) | L93: Bulk Fuel Storage Facility | M93: General Arrangement | N93: =K93&" - "&L93&" - "&M93&" - "&J93 -> Emergency Power Generation (Main Plant) - Bulk Fuel Storage Facility - General Arrangement - Sht 1 of 8 | Q93: =IFERROR(VLOOKUP(PPE_PH1_CDDL[[#This Row],[RDMC Document Number]],[3]Docs!$B:$F,4,0),"No Placeholder Yet") -> RES - Reserved Placeholder | R93: =IFERROR(VLOOKUP(PPE_PH1_CDDL[[#This Row],[RDMC Document Number]],[3]Docs!$B:$F,5,0),"No Placeholder Yet") -> Pending | S93: =IF(AND(O93<>"",P93<>"",R93="Approved"),100%, IF(AND(O93<>"",P93<>""),66.67%, IF(O93<>"",33.33%, 0))) -> 0 | T93: IS | V93: TENDER | W93: Bulk Fuel Storage Facility | X93: General Arrangement | AB93: Pending
A94: 6105A | B94: K124 | C94: 6260 | D94: E | E94: GAD | F94: 0006 | G94: A | H94: =A94&B94&"-"&C94&"-"&D94&E94&"-"&F94 -> 6105AK124-6260-EGAD-0006 | I94: ="Q24050972"&"-"&"07"&"-"&C94&"-"&D94&"-"&E94&"-"&F94 -> Q24050972-07-6260-E-GAD-0006 | J94: Sht 2 of 8 | K94: =VLOOKUP(C94,'PPE WBS Codes'!$E$3:$F$79,2,0) -> Emergency Power Generation (Main Plant) | L94: Pump house - Fuel Polish Isometric Arrangement | M94: General Arrangement | N94: =K94&" - "&L94&" - "&M94&" - "&J94 -> Emergency Power Generation (Main Plant) - Pump house - Fuel Polish Isometric Arrangement - General Arrangement - Sht 2 of 8 | Q94: =IFERROR(VLOOKUP(PPE_PH1_CDDL[[#This Row],[RDMC Document Number]],[3]Docs!$B:$F,4,0),"No Placeholder Yet") -> RES - Reserved Placeholder | R94: =IFERROR(VLOOKUP(PPE_PH1_CDDL[[#This Row],[RDMC Document Number]],[3]Docs!$B:$F,5,0),"No Placeholder Yet") -> Pending | S94: =IF(AND(O94<>"",P94<>"",R94="Approved"),100%, IF(AND(O94<>"",P94<>""),66.67%, IF(O94<>"",33.33%, 0))) -> 0 | T94: IS | V94: TENDER | W94: Bulk Fuel Storage Facility | X94: General Arrangement | AB94: Pending
A95: 6105A | B95: K124 | C95: 6260 | D95: E | E95: GAD | F95: 0007 | G95: A | H95: =A95&B95&"-"&C95&"-"&D95&E95&"-"&F95 -> 6105AK124-6260-EGAD-0007 | I95: ="Q24050972"&"-"&"07"&"-"&C95&"-"&D95&"-"&E95&"-"&F95 -> Q24050972-07-6260-E-GAD-0007 | J95: Sht 3 of 8 | K95: =VLOOKUP(C95,'PPE WBS Codes'!$E$3:$F$79,2,0) -> Emergency Power Generation (Main Plant) | L95: Bulk Fuel Storage Facility - Pump House - Fuel Polishing System | M95: General Arrangement | N95: =K95&" - "&L95&" - "&M95&" - "&J95 -> Emergency Power Generation (Main Plant) - Bulk Fuel Storage Facility - Pump House - Fuel Polishing System - General Arrangement - Sht 3 of 8 | Q95: =IFERROR(VLOOKUP(PPE_PH1_CDDL[[#This Row],[RDMC Document Number]],[3]Docs!$B:$F,4,0),"No Placeholder Yet") -> RES - Reserved Placeholder | R95: =IFERROR(VLOOKUP(PPE_PH1_CDDL[[#This Row],[RDMC Document Number]],[3]Docs!$B:$F,5,0),"No Placeholder Yet") -> Pending | S95: =IF(AND(O95<>"",P95<>"",R95="Approved"),100%, IF(AND(O95<>"",P95<>""),66.67%, IF(O95<>"",33.33%, 0))) -> 0 | T95: IS | V95: TENDER | W95: Bulk Fuel Storage Facility | X95: General Arrangement | AB95: Pending
A96: 6105A | B96: K124 | C96: 6260 | D96: E | E96: GAD | F96: 0008 | G96: A | H96: =A96&B96&"-"&C96&"-"&D96&E96&"-"&F96 -> 6105AK124-6260-EGAD-0008 | I96: ="Q24050972"&"-"&"07"&"-"&C96&"-"&D96&"-"&E96&"-"&F96 -> Q24050972-07-6260-E-GAD-0008 | J96: Sht 4 of 8 | K96: =VLOOKUP(C96,'PPE WBS Codes'!$E$3:$F$79,2,0) -> Emergency Power Generation (Main Plant) | L96: Bulk Fuel Storage Facility - Pump House - Fuel Transfer | M96: General Arrangement | N96: =K96&" - "&L96&" - "&M96&" - "&J96 -> Emergency Power Generation (Main Plant) - Bulk Fuel Storage Facility - Pump House - Fuel Transfer - General Arrangement - Sht 4 of 8 | Q96: =IFERROR(VLOOKUP(PPE_PH1_CDDL[[#This Row],[RDMC Document Number]],[3]Docs!$B:$F,4,0),"No Placeholder Yet") -> RES - Reserved Placeholder | R96: =IFERROR(VLOOKUP(PPE_PH1_CDDL[[#This Row],[RDMC Document Number]],[3]Docs!$B:$F,5,0),"No Placeholder Yet") -> Pending | S96: =IF(AND(O96<>"",P96<>"",R96="Approved"),100%, IF(AND(O96<>"",P96<>""),66.67%, IF(O96<>"",33.33%, 0))) -> 0 | T96: IS | V96: TENDER | W96: Bulk Fuel Storage Facility | X96: General Arrangement | AB96: Pending
A97: 6105A | B97: K124 | C97: 6260 | D97: E | E97: GAD | F97: 0009 | G97: A | H97: =A97&B97&"-"&C97&"-"&D97&E97&"-"&F97 -> 6105AK124-6260-EGAD-0009 | I97: ="Q24050972"&"-"&"07"&"-"&C97&"-"&D97&"-"&E97&"-"&F97 -> Q24050972-07-6260-E-GAD-0009 | J97: Sht 5 of 8 | K97: =VLOOKUP(C97,'PPE WBS Codes'!$E$3:$F$79,2,0) -> Emergency Power Generation (Main Plant) | L97: Bulk Fuel Storage Facility - Pump House - Fuel Transfer | M97: General Arrangement | N97: =K97&" - "&L97&" - "&M97&" - "&J97 -> Emergency Power Generation (Main Plant) - Bulk Fuel Storage Facility - Pump House - Fuel Transfer - General Arrangement - Sht 5 of 8 | Q97: =IFERROR(VLOOKUP(PPE_PH1_CDDL[[#This Row],[RDMC Document Number]],[3]Docs!$B:$F,4,0),"No Placeholder Yet") -> RES - Reserved Placeholder | R97: =IFERROR(VLOOKUP(PPE_PH1_CDDL[[#This Row],[RDMC Document Number]],[3]Docs!$B:$F,5,0),"No Placeholder Yet") -> Pending | S97: =IF(AND(O97<>"",P97<>"",R97="Approved"),100%, IF(AND(O97<>"",P97<>""),66.67%, IF(O97<>"",33.33%, 0))) -> 0 | T97: IS | V97: TENDER | W97: Bulk Fuel Storage Facility | X97: General Arrangement | AB97: Pending
A98: 6105A | B98: K124 | C98: 6260 | D98: E | E98: GAD | F98: 0010 | G98: A | H98: =A98&B98&"-"&C98&"-"&D98&E98&"-"&F98 -> 6105AK124-6260-EGAD-0010 | I98: ="Q24050972"&"-"&"07"&"-"&C98&"-"&D98&"-"&E98&"-"&F98 -> Q24050972-07-6260-E-GAD-0010 | J98: Sht 6 of 8 | K98: =VLOOKUP(C98,'PPE WBS Codes'!$E$3:$F$79,2,0) -> Emergency Power Generation (Main Plant) | L98: Pump house - Off-load system Isometric Arrangement | M98: General Arrangement | N98: =K98&" - "&L98&" - "&M98&" - "&J98 -> Emergency Power Generation (Main Plant) - Pump house - Off-load system Isometric Arrangement - General Arrangement - Sht 6 of 8 | Q98: =IFERROR(VLOOKUP(PPE_PH1_CDDL[[#This Row],[RDMC Document Number]],[3]Docs!$B:$F,4,0),"No Placeholder Yet") -> RES - Reserved Placeholder | R98: =IFERROR(VLOOKUP(PPE_PH1_CDDL[[#This Row],[RDMC Document Number]],[3]Docs!$B:$F,5,0),"No Placeholder Yet") -> Pending | S98: =IF(AND(O98<>"",P98<>"",R98="Approved"),100%, IF(AND(O98<>"",P98<>""),66.67%, IF(O98<>"",33.33%, 0))) -> 0 | T98: IS | V98: TENDER | W98: Bulk Fuel Storage Facility | X98: General Arrangement | AB98: Pending
A99: 6105A | B99: K124 | C99: 6260 | D99: E | E99: GAD | F99: 0011 | G99: A | H99: =A99&B99&"-"&C99&"-"&D99&E99&"-"&F99 -> 6105AK124-6260-EGAD-0011 | I99: ="Q24050972"&"-"&"07"&"-"&C99&"-"&D99&"-"&E99&"-"&F99 -> Q24050972-07-6260-E-GAD-0011 | J99: Sht 7 of 8 | K99: =VLOOKUP(C99,'PPE WBS Codes'!$E$3:$F$79,2,0) -> Emergency Power Generation (Main Plant) | L99: Bulk Fuel Offloading and Distribution System | M99: General Arrangement | N99: =K99&" - "&L99&" - "&M99&" - "&J99 -> Emergency Power Generation (Main Plant) - Bulk Fuel Offloading and Distribution System - General Arrangement - Sht 7 of 8 | Q99: =IFERROR(VLOOKUP(PPE_PH1_CDDL[[#This Row],[RDMC Document Number]],[3]Docs!$B:$F,4,0),"No Placeholder Yet") -> RES - Reserved Placeholder | R99: =IFERROR(VLOOKUP(PPE_PH1_CDDL[[#This Row],[RDMC Document Number]],[3]Docs!$B:$F,5,0),"No Placeholder Yet") -> Pending | S99: =IF(AND(O99<>"",P99<>"",R99="Approved"),100%, IF(AND(O99<>"",P99<>""),66.67%, IF(O99<>"",33.33%, 0))) -> 0 | T99: IS | V99: TENDER | W99: Bulk Fuel Storage Facility | X99: General Arrangement | AB99: Pending
A100: 6105A | B100: K124 | C100: 6260 | D100: E | E100: GAD | F100: 0012 | G100: A | H100: =A100&B100&"-"&C100&"-"&D100&E100&"-"&F100 -> 6105AK124-6260-EGAD-0012 | I100: ="Q24050972"&"-"&"08"&"-"&C100&"-"&D100&"-"&E100&"-"&F100 -> Q24050972-08-6260-E-GAD-0012 | J100: Sht 8 of 8 | K100: =VLOOKUP(C100,'PPE WBS Codes'!$E$3:$F$79,2,0) -> Emergency Power Generation (Main Plant) | L100: Bulk Fuel Storage Facility-Pump House-Off-Load System | M100: General Arrangement | N100: =K100&" - "&L100&" - "&M100&" - "&J100 -> Emergency Power Generation (Main Plant) - Bulk Fuel Storage Facility-Pump House-Off-Load System - General Arrangement - Sht 8 of 8 | Q100: =IFERROR(VLOOKUP(PPE_PH1_CDDL[[#This Row],[RDMC Document Number]],[3]Docs!$B:$F,4,0),"No Placeholder Yet") -> RES - Reserved Placeholder | R100: =IFERROR(VLOOKUP(PPE_PH1_CDDL[[#This Row],[RDMC Document Number]],[3]Docs!$B:$F,5,0),"No Placeholder Yet") -> Pending | S100: =IF(AND(O100<>"",P100<>"",R100="Approved"),100%, IF(AND(O100<>"",P100<>""),66.67%, IF(O100<>"",33.33%, 0))) -> 0 | T100: CLR | V100: TENDER | W100: Bulk Fuel Storage Facility | X100: General Arrangement | AB100: Pending
A101: 6105A | B101: K124 | C101: 6262 | D101: M | E101: GAD | F101: 0001 | G101: A | H101: =A101&B101&"-"&C101&"-"&D101&E101&"-"&F101 -> 6105AK124-6262-MGAD-0001 | I101: ="Q24050972"&"-"&"07"&"-"&C101&"-"&D101&"-"&E101&"-"&F101 -> Q24050972-07-6262-M-GAD-0001 | J101: Sht 1 of 1 | K101: =VLOOKUP(C101,'PPE WBS Codes'!$E$3:$F$79,2,0) -> Emergency Power Substation 1 and Control Room 1 | L101: 11kVA MV E-house type 1A | M101: External Views | N101: =K101&" - "&L101&" - "&M101&" - "&J101 -> Emergency Power Substation 1 and Control Room 1 - 11kVA MV E-house type 1A - External Views - Sht 1 of 1 | Q101: =IFERROR(VLOOKUP(PPE_PH1_CDDL[[#This Row],[RDMC Document Number]],[3]Docs!$B:$F,4,0),"No Placeholder Yet") -> RES - Reserved Placeholder | R101: =IFERROR(VLOOKUP(PPE_PH1_CDDL[[#This Row],[RDMC Document Number]],[3]Docs!$B:$F,5,0),"No Placeholder Yet") -> Pending | S101: =IF(AND(O101<>"",P101<>"",R101="Approved"),100%, IF(AND(O101<>"",P101<>""),66.67%, IF(O101<>"",33.33%, 0))) -> 0 | T101: CLR | V101: TENDER | W101: MV E-house | X101: External Views | AB101: Pending
A102: 6105A | B102: K124 | C102: 6262 | D102: M | E102: GAD | F102: 0003 | G102: A | H102: =A102&B102&"-"&C102&"-"&D102&E102&"-"&F102 -> 6105AK124-6262-MGAD-0003 | I102: ="Q24050972"&"-"&"07"&"-"&C102&"-"&D102&"-"&E102&"-"&F102 -> Q24050972-07-6262-M-GAD-0003 | J102: Sht 1 of 1 | K102: =VLOOKUP(C102,'PPE WBS Codes'!$E$3:$F$79,2,0) -> Emergency Power Substation 1 and Control Room 1 | L102: 11kVA MV E-house type 1A | M102: Plan Views | N102: =K102&" - "&L102&" - "&M102&" - "&J102 -> Emergency Power Substation 1 and Control Room 1 - 11kVA MV E-house type 1A - Plan Views - Sht 1 of 1 | Q102: =IFERROR(VLOOKUP(PPE_PH1_CDDL[[#This Row],[RDMC Document Number]],[3]Docs!$B:$F,4,0),"No Placeholder Yet") -> RES - Reserved Placeholder | R102: =IFERROR(VLOOKUP(PPE_PH1_CDDL[[#This Row],[RDMC Document Number]],[3]Docs!$B:$F,5,0),"No Placeholder Yet") -> Pending | S102: =IF(AND(O102<>"",P102<>"",R102="Approved"),100%, IF(AND(O102<>"",P102<>""),66.67%, IF(O102<>"",33.33%, 0))) -> 0 | T102: CLR | V102: TENDER | W102: MV E-house | X102: Plan Views | AB102: Pending
A103: 6105A | B103: K124 | C103: 6262 | D103: M | E103: GAD | F103: 0004 | G103: A | H103: =A103&B103&"-"&C103&"-"&D103&E103&"-"&F103 -> 6105AK124-6262-MGAD-0004 | I103: ="Q24050972"&"-"&"07"&"-"&C103&"-"&D103&"-"&E103&"-"&F103 -> Q24050972-07-6262-M-GAD-0004 | J103: Sht 1 of 1 | K103: =VLOOKUP(C103,'PPE WBS Codes'!$E$3:$F$79,2,0) -> Emergency Power Substation 1 and Control Room 1 | L103: 11kVA MV E-house type 1A | M103: Paint Schedule | N103: =K103&" - "&L103&" - "&M103&" - "&J103 -> Emergency Power Substation 1 and Control Room 1 - 11kVA MV E-house type 1A - Paint Schedule - Sht 1 of 1 | Q103: =IFERROR(VLOOKUP(PPE_PH1_CDDL[[#This Row],[RDMC Document Number]],[3]Docs!$B:$F,4,0),"No Placeholder Yet") -> RES - Reserved Placeholder | R103: =IFERROR(VLOOKUP(PPE_PH1_CDDL[[#This Row],[RDMC Document Number]],[3]Docs!$B:$F,5,0),"No Placeholder Yet") -> Pending | S103: =IF(AND(O103<>"",P103<>"",R103="Approved"),100%, IF(AND(O103<>"",P103<>""),66.67%, IF(O103<>"",33.33%, 0))) -> 0 | T103: CLR | V103: TENDER | W103: MV E-house | X103: Paint Schedule | AB103: Pending
A104: 6105A | B104: K124 | C104: 6262 | D104: M | E104: GAD | F104: 0005 | G104: A | H104: =A104&B104&"-"&C104&"-"&D104&E104&"-"&F104 -> 6105AK124-6262-MGAD-0005 | I104: ="Q24050972"&"-"&"07"&"-"&C104&"-"&D104&"-"&E104&"-"&F104 -> Q24050972-07-6262-M-GAD-0005 | J104: Sht 1 of 1 | K104: =VLOOKUP(C104,'PPE WBS Codes'!$E$3:$F$79,2,0) -> Emergency Power Substation 1 and Control Room 1 | L104: 11kVA MV E-house type 1A | M104: Signage Schedule | N104: =K104&" - "&L104&" - "&M104&" - "&J104 -> Emergency Power Substation 1 and Control Room 1 - 11kVA MV E-house type 1A - Signage Schedule - Sht 1 of 1 | Q104: =IFERROR(VLOOKUP(PPE_PH1_CDDL[[#This Row],[RDMC Document Number]],[3]Docs!$B:$F,4,0),"No Placeholder Yet") -> RES - Reserved Placeholder | R104: =IFERROR(VLOOKUP(PPE_PH1_CDDL[[#This Row],[RDMC Document Number]],[3]Docs!$B:$F,5,0),"No Placeholder Yet") -> Pending | S104: =IF(AND(O104<>"",P104<>"",R104="Approved"),100%, IF(AND(O104<>"",P104<>""),66.67%, IF(O104<>"",33.33%, 0))) -> 0 | T104: CLR | V104: TENDER | W104: MV E-house | X104: Signage Schedule | AB104: Pending
A105: 6105A | B105: K124 | C105: 6262 | D105: M | E105: GAD | F105: 0010 | G105: A | H105: =A105&B105&"-"&C105&"-"&D105&E105&"-"&F105 -> 6105AK124-6262-MGAD-0010 | I105: ="Q24050972"&"-"&"08"&"-"&C105&"-"&D105&"-"&E105&"-"&F105 -> Q24050972-08-6262-M-GAD-0010 | J105: Sht 1 of 1 | K105: =VLOOKUP(C105,'PPE WBS Codes'!$E$3:$F$79,2,0) -> Emergency Power Substation 1 and Control Room 1 | L105: 11kVA MV E-house type 1B | M105: Signage Schedule | N105: =K105&" - "&L105&" - "&M105&" - "&J105 -> Emergency Power Substation 1 and Control Room 1 - 11kVA MV E-house type 1B - Signage Schedule - Sht 1 of 1 | Q105: =IFERROR(VLOOKUP(PPE_PH1_CDDL[[#This Row],[RDMC Document Number]],[3]Docs!$B:$F,4,0),"No Placeholder Yet") -> RES - Reserved Placeholder | R105: =IFERROR(VLOOKUP(PPE_PH1_CDDL[[#This Row],[RDMC Document Number]],[3]Docs!$B:$F,5,0),"No Placeholder Yet") -> Pending | S105: =IF(AND(O105<>"",P105<>"",R105="Approved"),100%, IF(AND(O105<>"",P105<>""),66.67%, IF(O105<>"",33.33%, 0))) -> 0 | T105: CLR | V105: TENDER | W105: MV E-house | X105: Signage Schedule | AB105: Pending
A106: 6105A | B106: K124 | C106: 6262 | D106: M | E106: GAD | F106: 0006 | G106: A | H106: =A106&B106&"-"&C106&"-"&D106&E106&"-"&F106 -> 6105AK124-6262-MGAD-0006 | I106: ="Q24050972"&"-"&"08"&"-"&C106&"-"&D106&"-"&E106&"-"&F106 -> Q24050972-08-6262-M-GAD-0006 | J106: Sht 1 of 1 | K106: =VLOOKUP(C106,'PPE WBS Codes'!$E$3:$F$79,2,0) -> Emergency Power Substation 1 and Control Room 1 | L106: 11kVA MV E-house type 1B | M106: External Views | N106: =K106&" - "&L106&" - "&M106&" - "&J106 -> Emergency Power Substation 1 and Control Room 1 - 11kVA MV E-house type 1B - External Views - Sht 1 of 1 | Q106: =IFERROR(VLOOKUP(PPE_PH1_CDDL[[#This Row],[RDMC Document Number]],[3]Docs!$B:$F,4,0),"No Placeholder Yet") -> RES - Reserved Placeholder | R106: =IFERROR(VLOOKUP(PPE_PH1_CDDL[[#This Row],[RDMC Document Number]],[3]Docs!$B:$F,5,0),"No Placeholder Yet") -> Pending | S106: =IF(AND(O106<>"",P106<>"",R106="Approved"),100%, IF(AND(O106<>"",P106<>""),66.67%, IF(O106<>"",33.33%, 0))) -> 0 | T106: CLR | V106: TENDER | W106: MV E-house | X106: External Views | AB106: Pending
A107: 6105A | B107: K124 | C107: 6262 | D107: M | E107: GAD | F107: 0007 | G107: A | H107: =A107&B107&"-"&C107&"-"&D107&E107&"-"&F107 -> 6105AK124-6262-MGAD-0007 | I107: ="Q24050972"&"-"&"08"&"-"&C107&"-"&D107&"-"&E107&"-"&F107 -> Q24050972-08-6262-M-GAD-0007 | J107: Sht 1 of 1 | K107: =VLOOKUP(C107,'PPE WBS Codes'!$E$3:$F$79,2,0) -> Emergency Power Substation 1 and Control Room 1 | L107: 11kVA MV E-house type 1B | M107: Internal Views | N107: =K107&" - "&L107&" - "&M107&" - "&J107 -> Emergency Power Substation 1 and Control Room 1 - 11kVA MV E-house type 1B - Internal Views - Sht 1 of 1 | Q107: =IFERROR(VLOOKUP(PPE_PH1_CDDL[[#This Row],[RDMC Document Number]],[3]Docs!$B:$F,4,0),"No Placeholder Yet") -> RES - Reserved Placeholder | R107: =IFERROR(VLOOKUP(PPE_PH1_CDDL[[#This Row],[RDMC Document Number]],[3]Docs!$B:$F,5,0),"No Placeholder Yet") -> Pending | S107: =IF(AND(O107<>"",P107<>"",R107="Approved"),100%, IF(AND(O107<>"",P107<>""),66.67%, IF(O107<>"",33.33%, 0))) -> 0 | T107: CLR | V107: TENDER | W107: MV E-house | X107: Internall Views | AB107: Pending
A108: 6105A | B108: K124 | C108: 6262 | D108: M | E108: GAD | F108: 0008 | G108: A | H108: =A108&B108&"-"&C108&"-"&D108&E108&"-"&F108 -> 6105AK124-6262-MGAD-0008 | I108: ="Q24050972"&"-"&"08"&"-"&C108&"-"&D108&"-"&E108&"-"&F108 -> Q24050972-08-6262-M-GAD-0008 | J108: Sht 1 of 1 | K108: =VLOOKUP(C108,'PPE WBS Codes'!$E$3:$F$79,2,0) -> Emergency Power Substation 1 and Control Room 1 | L108: 11kVA MV E-house type 1B | M108: Plan Views | N108: =K108&" - "&L108&" - "&M108&" - "&J108 -> Emergency Power Substation 1 and Control Room 1 - 11kVA MV E-house type 1B - Plan Views - Sht 1 of 1 | Q108: =IFERROR(VLOOKUP(PPE_PH1_CDDL[[#This Row],[RDMC Document Number]],[3]Docs!$B:$F,4,0),"No Placeholder Yet") -> RES - Reserved Placeholder | R108: =IFERROR(VLOOKUP(PPE_PH1_CDDL[[#This Row],[RDMC Document Number]],[3]Docs!$B:$F,5,0),"No Placeholder Yet") -> Pending | S108: =IF(AND(O108<>"",P108<>"",R108="Approved"),100%, IF(AND(O108<>"",P108<>""),66.67%, IF(O108<>"",33.33%, 0))) -> 0 | T108: CLR | V108: TENDER | W108: MV E-house | X108: Plan Views | AB108: Pending
A109: 6105A | B109: K124 | C109: 6262 | D109: M | E109: GAD | F109: 0009 | G109: A | H109: =A109&B109&"-"&C109&"-"&D109&E109&"-"&F109 -> 6105AK124-6262-MGAD-0009 | I109: ="Q24050972"&"-"&"08"&"-"&C109&"-"&D109&"-"&E109&"-"&F109 -> Q24050972-08-6262-M-GAD-0009 | J109: Sht 1 of 1 | K109: =VLOOKUP(C109,'PPE WBS Codes'!$E$3:$F$79,2,0) -> Emergency Power Substation 1 and Control Room 1 | L109: 11kVA MV E-house type 1B | M109: Paint Schedule | N109: =K109&" - "&L109&" - "&M109&" - "&J109 -> Emergency Power Substation 1 and Control Room 1 - 11kVA MV E-house type 1B - Paint Schedule - Sht 1 of 1 | Q109: =IFERROR(VLOOKUP(PPE_PH1_CDDL[[#This Row],[RDMC Document Number]],[3]Docs!$B:$F,4,0),"No Placeholder Yet") -> RES - Reserved Placeholder | R109: =IFERROR(VLOOKUP(PPE_PH1_CDDL[[#This Row],[RDMC Document Number]],[3]Docs!$B:$F,5,0),"No Placeholder Yet") -> Pending | S109: =IF(AND(O109<>"",P109<>"",R109="Approved"),100%, IF(AND(O109<>"",P109<>""),66.67%, IF(O109<>"",33.33%, 0))) -> 0 | T109: CLR | V109: TENDER | W109: MV E-house | X109: Paint Schedule | AB109: Pending
A110: 6105A | B110: K124 | C110: 6286 | D110: E | E110: GAD | F110: 0001 | G110: A | H110: =A110&B110&"-"&C110&"-"&D110&E110&"-"&F110 -> 6105AK124-6286-EGAD-0001 | I110: ="Q24050972"&"-"&"08"&"-"&C110&"-"&D110&"-"&E110&"-"&F110 -> Q24050972-08-6286-E-GAD-0001 | J110: Sht 1 of 1 | K110: =VLOOKUP(C110,'PPE WBS Codes'!$E$3:$F$79,2,0) -> Primary Crushing | L110: Mining Substation | M110: General Arrangement | N110: =K110&" - "&L110&" - "&M110&" - "&J110 -> Primary Crushing - Mining Substation - General Arrangement - Sht 1 of 1 | Q110: =IFERROR(VLOOKUP(PPE_PH1_CDDL[[#This Row],[RDMC Document Number]],[3]Docs!$B:$F,4,0),"No Placeholder Yet") -> RES - Reserved Placeholder | R110: =IFERROR(VLOOKUP(PPE_PH1_CDDL[[#This Row],[RDMC Document Number]],[3]Docs!$B:$F,5,0),"No Placeholder Yet") -> Pending | S110: =IF(AND(O110<>"",P110<>"",R110="Approved"),100%, IF(AND(O110<>"",P110<>""),66.67%, IF(O110<>"",33.33%, 0))) -> 0 | T110: CLR | V110: TENDER | W110: Mining Substation | X110: General Arrangement | AB110: Pending
A111: 6105A | B111: K124 | C111: 6286 | D111: M | E111: GAD | F111: 0001 | G111: A | H111: =A111&B111&"-"&C111&"-"&D111&E111&"-"&F111 -> 6105AK124-6286-MGAD-0001 | I111: ="Q24050972"&"-"&"07"&"-"&C111&"-"&D111&"-"&E111&"-"&F111 -> Q24050972-07-6286-M-GAD-0001 | J111: Sht 1 of 1 | K111: =VLOOKUP(C111,'PPE WBS Codes'!$E$3:$F$79,2,0) -> Primary Crushing | L111: 11kVA MV E-house type 1A | M111: External Views | N111: =K111&" - "&L111&" - "&M111&" - "&J111 -> Primary Crushing - 11kVA MV E-house type 1A - External Views - Sht 1 of 1 | Q111: =IFERROR(VLOOKUP(PPE_PH1_CDDL[[#This Row],[RDMC Document Number]],[3]Docs!$B:$F,4,0),"No Placeholder Yet") -> RES - Reserved Placeholder | R111: =IFERROR(VLOOKUP(PPE_PH1_CDDL[[#This Row],[RDMC Document Number]],[3]Docs!$B:$F,5,0),"No Placeholder Yet") -> Pending | S111: =IF(AND(O111<>"",P111<>"",R111="Approved"),100%, IF(AND(O111<>"",P111<>""),66.67%, IF(O111<>"",33.33%, 0))) -> 0 | T111: CLR | V111: TENDER | W111: 11kVA MV E-house type 1A | X111: External Views | AB111: Pending
A112: 6105A | B112: K124 | C112: 6286 | D112: M | E112: GAD | F112: 0002 | G112: A | H112: =A112&B112&"-"&C112&"-"&D112&E112&"-"&F112 -> 6105AK124-6286-MGAD-0002 | I112: ="Q24050972"&"-"&"07"&"-"&C112&"-"&D112&"-"&E112&"-"&F112 -> Q24050972-07-6286-M-GAD-0002 | J112: Sht 1 of 1 | K112: =VLOOKUP(C112,'PPE WBS Codes'!$E$3:$F$79,2,0) -> Primary Crushing | L112: 11kVA MV E-house type 1A | M112: Internal Views | N112: =K112&" - "&L112&" - "&M112&" - "&J112 -> Primary Crushing - 11kVA MV E-house type 1A - Internal Views - Sht 1 of 1 | Q112: =IFERROR(VLOOKUP(PPE_PH1_CDDL[[#This Row],[RDMC Document Number]],[3]Docs!$B:$F,4,0),"No Placeholder Yet") -> RES - Reserved Placeholder | R112: =IFERROR(VLOOKUP(PPE_PH1_CDDL[[#This Row],[RDMC Document Number]],[3]Docs!$B:$F,5,0),"No Placeholder Yet") -> Pending | S112: =IF(AND(O112<>"",P112<>"",R112="Approved"),100%, IF(AND(O112<>"",P112<>""),66.67%, IF(O112<>"",33.33%, 0))) -> 0 | T112: CLR | V112: TENDER | W112: 11kVA MV E-house type 1A | X112: Internall Views | AB112: Pending
A113: 6105A | B113: K124 | C113: 6286 | D113: M | E113: GAD | F113: 0003 | G113: A | H113: =A113&B113&"-"&C113&"-"&D113&E113&"-"&F113 -> 6105AK124-6286-MGAD-0003 | I113: ="Q24050972"&"-"&"07"&"-"&C113&"-"&D113&"-"&E113&"-"&F113 -> Q24050972-07-6286-M-GAD-0003 | J113: Sht 1 of 1 | K113: =VLOOKUP(C113,'PPE WBS Codes'!$E$3:$F$79,2,0) -> Primary Crushing | L113: 11kVA MV E-house type 1A | M113: Plan Views | N113: =K113&" - "&L113&" - "&M113&" - "&J113 -> Primary Crushing - 11kVA MV E-house type 1A - Plan Views - Sht 1 of 1 | Q113: =IFERROR(VLOOKUP(PPE_PH1_CDDL[[#This Row],[RDMC Document Number]],[3]Docs!$B:$F,4,0),"No Placeholder Yet") -> RES - Reserved Placeholder | R113: =IFERROR(VLOOKUP(PPE_PH1_CDDL[[#This Row],[RDMC Document Number]],[3]Docs!$B:$F,5,0),"No Placeholder Yet") -> Pending | S113: =IF(AND(O113<>"",P113<>"",R113="Approved"),100%, IF(AND(O113<>"",P113<>""),66.67%, IF(O113<>"",33.33%, 0))) -> 0 | T113: CLR | V113: TENDER | W113: 11kVA MV E-house type 1A | X113: Plan Views | AB113: Pending
A114: 6105A | B114: K124 | C114: 6286 | D114: M | E114: GAD | F114: 0004 | G114: A | H114: =A114&B114&"-"&C114&"-"&D114&E114&"-"&F114 -> 6105AK124-6286-MGAD-0004 | I114: ="Q24050972"&"-"&"07"&"-"&C114&"-"&D114&"-"&E114&"-"&F114 -> Q24050972-07-6286-M-GAD-0004 | J114: Sht 1 of 1 | K114: =VLOOKUP(C114,'PPE WBS Codes'!$E$3:$F$79,2,0) -> Primary Crushing | L114: 11kVA MV E-house type 1A | M114: Paint Schedule | N114: =K114&" - "&L114&" - "&M114&" - "&J114 -> Primary Crushing - 11kVA MV E-house type 1A - Paint Schedule - Sht 1 of 1 | Q114: =IFERROR(VLOOKUP(PPE_PH1_CDDL[[#This Row],[RDMC Document Number]],[3]Docs!$B:$F,4,0),"No Placeholder Yet") -> RES - Reserved Placeholder | R114: =IFERROR(VLOOKUP(PPE_PH1_CDDL[[#This Row],[RDMC Document Number]],[3]Docs!$B:$F,5,0),"No Placeholder Yet") -> Pending | S114: =IF(AND(O114<>"",P114<>"",R114="Approved"),100%, IF(AND(O114<>"",P114<>""),66.67%, IF(O114<>"",33.33%, 0))) -> 0 | T114: CLR | V114: TENDER | W114: 11kVA MV E-house type 1A | X114: Paint Schedule | AB114: Pending
A115: 6105A | B115: K124 | C115: 6286 | D115: M | E115: GAD | F115: 0005 | G115: A | H115: =A115&B115&"-"&C115&"-"&D115&E115&"-"&F115 -> 6105AK124-6286-MGAD-0005 | I115: ="Q24050972"&"-"&"07"&"-"&C115&"-"&D115&"-"&E115&"-"&F115 -> Q24050972-07-6286-M-GAD-0005 | J115: Sht 1 of 1 | K115: =VLOOKUP(C115,'PPE WBS Codes'!$E$3:$F$79,2,0) -> Primary Crushing | L115: 11kVA MV E-house type 1A | M115: Signage Schedule | N115: =K115&" - "&L115&" - "&M115&" - "&J115 -> Primary Crushing - 11kVA MV E-house type 1A - Signage Schedule - Sht 1 of 1 | Q115: =IFERROR(VLOOKUP(PPE_PH1_CDDL[[#This Row],[RDMC Document Number]],[3]Docs!$B:$F,4,0),"No Placeholder Yet") -> RES - Reserved Placeholder | R115: =IFERROR(VLOOKUP(PPE_PH1_CDDL[[#This Row],[RDMC Document Number]],[3]Docs!$B:$F,5,0),"No Placeholder Yet") -> Pending | S115: =IF(AND(O115<>"",P115<>"",R115="Approved"),100%, IF(AND(O115<>"",P115<>""),66.67%, IF(O115<>"",33.33%, 0))) -> 0 | T115: CLR | V115: TENDER | W115: 11kVA MV E-house type 1A | X115: Signage Schedule | AB115: Pending
A116: 6105A | B116: K124 | C116: 6286 | D116: M | E116: GAD | F116: 0006 | G116: A | H116: =A116&B116&"-"&C116&"-"&D116&E116&"-"&F116 -> 6105AK124-6286-MGAD-0006 | I116: ="Q24050972"&"-"&"07"&"-"&C116&"-"&D116&"-"&E116&"-"&F116 -> Q24050972-07-6286-M-GAD-0006 | J116: Sht 1 of 1 | K116: =VLOOKUP(C116,'PPE WBS Codes'!$E$3:$F$79,2,0) -> Primary Crushing | L116: 11kVA MV E-house type 1B | M116: External Views | N116: =K116&" - "&L116&" - "&M116&" - "&J116 -> Primary Crushing - 11kVA MV E-house type 1B - External Views - Sht 1 of 1 | Q116: =IFERROR(VLOOKUP(PPE_PH1_CDDL[[#This Row],[RDMC Document Number]],[3]Docs!$B:$F,4,0),"No Placeholder Yet") -> RES - Reserved Placeholder | R116: =IFERROR(VLOOKUP(PPE_PH1_CDDL[[#This Row],[RDMC Document Number]],[3]Docs!$B:$F,5,0),"No Placeholder Yet") -> Pending | S116: =IF(AND(O116<>"",P116<>"",R116="Approved"),100%, IF(AND(O116<>"",P116<>""),66.67%, IF(O116<>"",33.33%, 0))) -> 0 | T116: CLR | V116: TENDER | W116: 11kVA MV E-house type 1B | X116: External Views | AB116: Pending
A117: 6105A | B117: K124 | C117: 6286 | D117: M | E117: GAD | F117: 0007 | G117: A | H117: =A117&B117&"-"&C117&"-"&D117&E117&"-"&F117 -> 6105AK124-6286-MGAD-0007 | I117: ="Q24050972"&"-"&"07"&"-"&C117&"-"&D117&"-"&E117&"-"&F117 -> Q24050972-07-6286-M-GAD-0007 | J117: Sht 1 of 1 | K117: =VLOOKUP(C117,'PPE WBS Codes'!$E$3:$F$79,2,0) -> Primary Crushing | L117: 11kVA MV E-house type 1B | M117: Internal Views | N117: =K117&" - "&L117&" - "&M117&" - "&J117 -> Primary Crushing - 11kVA MV E-house type 1B - Internal Views - Sht 1 of 1 | Q117: =IFERROR(VLOOKUP(PPE_PH1_CDDL[[#This Row],[RDMC Document Number]],[3]Docs!$B:$F,4,0),"No Placeholder Yet") -> RES - Reserved Placeholder | R117: =IFERROR(VLOOKUP(PPE_PH1_CDDL[[#This Row],[RDMC Document Number]],[3]Docs!$B:$F,5,0),"No Placeholder Yet") -> Pending | S117: =IF(AND(O117<>"",P117<>"",R117="Approved"),100%, IF(AND(O117<>"",P117<>""),66.67%, IF(O117<>"",33.33%, 0))) -> 0 | T117: CLR | V117: TENDER | W117: 11kVA MV E-house type 1B | X117: Internall Views | AB117: Pending
...

Sheet PPE WBS Codes
A1: L1 | B1: L2 | C1: L3 | D1: L4 | E1: Code | F1: Reko Diq Copper - Gold Project Facility Name
A2: 0 | B2: 0 | C2: 0 | D2: 0 | E2: 0000 | F2: General | H2: =E2&" - "&F2 -> 0000 - General
A3: 0 | B3: 1 | C3: 0 | D3: 0 | E3: 0100 | F3: Project Site Wide | H3: =E3&" - "&F3 -> 0100 - Project Site Wide
A4: 5 | B4: 3 | C4: 5 | D4: 0 | E4: 5350 | F4: Process Water Dams | H4: =E4&" - "&F4 -> 5350 - Process Water Dams
A5: 5 | B5: 3 | C5: 6 | D5: 0 | E5: 5360 | F5: Raw Water Dams | H5: =E5&" - "&F5 -> 5360 - Raw Water Dams
A6: 5 | B6: 3 | C6: 7 | D6: 0 | E6: 5370 | F6: Turkey Nests | H6: =E6&" - "&F6 -> 5370 - Turkey Nests
A7: 5 | B7: 5 | C7: 3 | D7: 0 | E7: 5530 | F7: Village Sewage | H7: =E7&" - "&F7 -> 5530 - Village Sewage
A8: 5 | B8: 6 | C8: 3 | D8: 0 | E8: 5630 | F8: Potable Water Treatment | H8: =E8&" - "&F8 -> 5630 - Potable Water Treatment
A9: 6 | B9: 1 | C9: 8 | D9: 0 | E9: 6180 | F9: Village | H9: =E9&" - "&F9 -> 6180 - Village
A10: 6 | B10: 1 | C10: 8 | D10: 1 | E10: 6181 | F10: Accommodation | H10: =E10&" - "&F10 -> 6181 - Accommodation
A11: 6 | B11: 1 | C11: 8 | D11: 2 | E11: 6182 | F11: Mess Hall and Food Storage | H11: =E11&" - "&F11 -> 6182 - Mess Hall and Food Storage
A12: 6 | B12: 1 | C12: 8 | D12: 3 | E12: 6183 | F12: Leisure Amenities | H12: =E12&" - "&F12 -> 6183 - Leisure Amenities
A13: 6 | B13: 1 | C13: 8 | D13: 4 | E13: 6184 | F13: Laundry Facilities | H13: =E13&" - "&F13 -> 6184 - Laundry Facilities
A14: 6 | B14: 1 | C14: 8 | D14: 5 | E14: 6185 | F14: Potable Water and Water Treatment | H14: =E14&" - "&F14 -> 6185 - Potable Water and Water Treatment
A15: 6 | B15: 1 | C15: 8 | D15: 6 | E15: 6186 | F15: Firewater - Tank & Fire Fighting System | H15: =E15&" - "&F15 -> 6186 - Firewater - Tank & Fire Fighting System
... A20: 6 | B20: 2 | C20: 1 | D20: 0 | E20: 6210 | F20: Power Stations | H20: =E20&" - "&F20 -> 6210 - Power Stations
A21: 6 | B21: 2 | C21: 1 | D21: 2 | E21: 6212 | F21: Power Station 1 | H21: 6212 - Power Station 1
A22: 6 | B22: 2 | C22: 3 | D22: 0 | E22: 6230 | F22: High Voltage (220 kV) Transmission Lines | H22: 6230 - High Voltage (220 kV) Transmission Lines
A23: 6 | B23: 2 | C23: 4 | D23: 0 | E23: 6240 | F23: High Voltage Substations | H23: =E23&" - "&F23 -> 6240 - High Voltage Substations
A24: 6 | B24: 2 | C24: 4 | D24: 1 | E24: 6241 | F24: 33/220 kV Solar PV Substation | H24: =E24&" - "&F24 -> 6241 - 33/220 kV Solar PV Substation
A25: 6 | B25: 2 | C25: 4 | D25: 2 | E25: 6242 | F25: 33/220 kV Power Station Substation | H25: =E25&" - "&F25 -> 6242 - 33/220 kV Power Station Substation
A26: 6 | B26: 2 | C26: 4 | D26: 3 | E26: 6243 | F26: 220/33 kV Plant Main Substation | H26: =E26&" - "&F26 -> 6243 - 220/33 kV Plant Main Substation
A27: 6 | B27: 2 | C27: 5 | D27: 0 | E27: 6250 | F27: Power Conditioning Equipment | H27: =E27&" - "&F27 -> 6250 - Power Conditioning Equipment
A28: 6 | B28: 2 | C28: 5 | D28: 1 | E28: 6251 | F28: Load Bank | H28: =E28&" - "&F28 -> 6251 - Load Bank
A29: 6 | B29: 2 | C29: 5 | D29: 2 | E29: 6252 | F29: Harmonic Filters 1 | H29: =E29&" - "&F29 -> 6252 - Harmonic Filters 1
A30: 6 | B30: 2 | C30: 5 | D30: 3 | E30: 6253 | F30: Synchronous Condenser 1 | H30: =E30&" - "&F30 -> 6253 - Synchronous Condenser 1
A31: 6 | B31: 2 | C31: 5 | D31: 4 | E31: 6254 | F31: Battery Energy Storage System 1 | H31: =E31&" - "&F31 -> 6254 - Battery Energy Storage System 1
A32: 6 | B32: 2 | C32: 5 | D32: 5 | E32: 6255 | F32: Harmonic Filters 2 | H32: =E32&" - "&F32 -> 6255 - Harmonic Filters 2
A33: 6 | B33: 2 | C33: 5 | D33: 6 | E33: 6256 | F33: Synchronous Condenser 2 | H33: =E33&" - "&F33 -> 6256 - Synchronous Condenser 2
A34: 6 | B34: 2 | C34: 5 | D34: 7 | E34: 6257 | F34: Battery Energy Storage System 2 | H34: =E34&" - "&F34 -> 6257 - Battery Energy Storage System 2
... A79: 7 | B79: 3 | C79: 3 | D79: 7 | E79: 7337 | F79: Port Qasim PIBT Control Room | H79: =E79&" - "&F79 -> 7337 - Port Qasim PIBT Control Room

Sheet Rev10 RDMC WBS Areas
B1: Facility Level ID | E1: Facility Code | F1: Reko Diq Project Facility Name | G1: Engineering | H1: Procurement | I1: Contracts | J1: Construction Management
A2: L1 | B2: L2 | C2: L3 | D2: L4
A3: 0 | B3: 0 | C3: 0 | D3: 0 | E3: 0 | F3: General | G3: - | H3: - | I3: - | J3: -
A4: 0 | B4: 1 | C4: 0 | D4: 0 | E4: 100 | F4: Project Site Wide | G4: - | H4: - | I4: - | J4: -
A5: 1 | B5: 0 | C5: 0 | D5: 0 | E5: 1000 | F5: Mining - OP | G5: RDMC/Fluor | H5: RDMC/Fluor | I5: RDMC/Fluor | J5: RDMC/Fluor
A6: 1 | B6: 1 | C6: 0 | D6: 0 | E6: 1100 | F6: Open Pit Mine | G6: RDMC/Fluo r | H6: RDMC/Fluo r | I6: RDMC/Fluo r | J6: RDMC/Fluo r
A7: 1 | B7: 1 | C7: 1 | D7: 0 | E7: 1110 | F7: Open Pit Mine Development | G7: RDMC | H7: RDMC | I7: RDMC | J7: RDMC
A8: 1 | B8: 1 | C8: 1 | D8: 1 | E8: 1111 | F8: Pre-Stripping | G8: RDMC | H8: RDMC | I8: RDMC | J8: RDMC
A9: 1 | B9: 1 | C9: 1 | D9: 2 | E9: 1112 | F9: Stockpiling | G9: RDMC | H9: RDMC | I9: RDMC | J9: RDMC
A10: 1 | B10: 1 | C10: 1 | D10: 3 | E10: 1113 | F10: Waste Dumps | G10: RDMC | H10: RDMC | I10: RDMC | J10: RDMC
A11: 1 | B11: 1 | C11: 1 | D11: 4 | E11: 1114 | F11: Run-of-Mine Pad | G11: RDMC | H11: RDMC | I11: RDMC | J11: RDMC
A12: 1 | B12: 1 | C12: 1 | D12: 5 | E12: 1115 | F12: Clearing, Grubbing and Topsoil Stockpiling | G12: RDMC | H12: RDMC | I12: RDMC | J12: RDMC
A13: 1 | B13: 1 | C13: 1 | D13: 9 | E13: 1119 | F13: Common Facilities and Services | G13: RDMC | H13: RDMC | I13: RDMC | J13: RDMC
A14: 1 | B14: 1 | C14: 2 | D14: 0 | E14: 1120 | F14: Open Pit Mining Equipment | G14: RDMC | H14: RDMC | I14: RDMC | J14: RDMC
... A846: 7 | B846: 1 | C846: 7 | D846: 1 | E846: 7171 | F846: Off-Site Desalinated Water Pipeline | G846: Future | H846: Future | I846: Future | J846: Future
A847: 7 | B847: 1 | C847: 7 | D847: 4 | E847: 7174 | F847: Off-Site Water Bulk Storage
A848: 7 | B848: 1 | C848: 7 | D848: 5 | E848: 7175 | F848: Off-Site Hamun-i-Mashkel (HIM) Bore Field | G848: Future | H848: Future | I848: Future | J848: Future
A849: 7 | B849: 1 | C849: 7 | D849: 6 | E849: 7176 | F849: Off-Site Borehole Fieldwater Pipeline - Hamun-i-Mashkel (HIM) | G849: Future | H849: Future | I849: Future | J849: Future
A850: 7 | B850: 1 | C850: 7 | D850: 7 | E850: 7177 | F850: Off-Site Fan Sediments Bore Field | G850: Fluor | H850: Fluor | I850: Fluor | J850: Fluor
A851: 7 | B851: 1 | C851: 7 | D851: 8 | E851: 7178 | F851: Off-Site Borehole Fieldwater Pipeline - Fan Sediments Main Line | G851: Fluor | H851: Fluor | I851: Fluor | J851: Fluor
A852: 7 | B852: 1 | C852: 7 | D852: 9 | E852: 7179 | F852: Off-Site Borehole Fieldwater Pipeline - Fan Sediments Construction Line | G852: RDMC | H852: RDMC | I852: Fluor | J852: Fluor
A853: 7 | B853: 1 | C853: 8 | D853: 0 | E853: 7180 | F853: Off-Site Services/Utilities | G853: RDMC | H853: RDMC | I853: RDMC | J853: RDMC
A854: 7 | B854: 1 | C854: 8 | D854: 1 | E854: 7181 | F854: Off-Site Fresh Water Distribution | G854: RDMC | H854: RDMC | I854: RDMC | J854: RDMC
A855: 7 | B855: 1 | C855: 8 | D855: 2 | E855: 7182 | F855: Off-Site Potable Water Distribution | G855: RDMC | H855: RDMC | I855: RDMC | J855: RDMC
A856: 7 | B856: 1 | C856: 8 | D856: 3 | E856: 7183 | F856: Off-Site Acid Rock Drainage (ARD) Water Distribution
A857: 7 | B857: 1 | C857: 8 | D857: 4 | E857: 7184 | F857: Off-Site Fire Water Distribution | G857: RDMC | H857: RDMC | I857: RDMC | J857: RDMC
A858: 7 | B858: 1 | C858: 8 | D858: 5 | E858: 7185 | F858: Off-Site Environmental Monitoring | G858: RDMC | H858: RDMC | I858: RDMC | J858: RDMC
A859: 7 | B859: 1 | C859: 8 | D859: 6 | E859: 7186 | F859: Off-Site Communications | G859: RDMC | H859: RDMC | I859: RDMC | J859: RDMC
A860: 7 | B860: 1 | C860: 8 | D860: 7 | E860: 7187 | F860: Off-Site Effluent Utilities | G860: RDMC | H860: RDMC | I860: RDMC | J860: RDMC
A861: 7 | B861: 1 | C861: 8 | D861: 8 | E861: 7188 | F861: Off-Site Other Utilities (Compressed Air & Propane, etc.) | G861: RDMC | H861: RDMC | I861: RDMC | J861: RDMC
A862: 7 | B862: 1 | C862: 9 | D862: 0 | E862: 7190 | F862: Off-Site Power Supply & Transmission
A863: 7 | B863: 1 | C863: 9 | D863: 1 | E863: 7191 | F863: Switchyard
A864: 7 | B864: 1 | C864: 9 | D864: 2 | E864: 7192 | F864: Off-Site Transmission
A865: 7 | B865: 1 | C865: 9 | D865: 3 | E865: 7193 | F865: Main Substation
A866: 7 | B866: 1 | C866: 9 | D866: 4 | E866: 7194 | F866: Power Generation
A867: 7 | B867: 1 | C867: 9 | D867: 9 | E867: 7199 | F867: Off-Site Power Facilities & Services
A868: 7 | B868: 2 | C868: 0 | D868: 0 | E868: 7200 | F868: Off-Site Port (Qasim & Gwadar) - (Not in Scope) | G868: - | H868: - | I868: - | J868: -
A869: 7 | B869: 2 | C869: 1 | D869: 0 | E869: 7210 | F869: Port Concentrate Handling | G869: - | H869: - | I869: - | J869: -
A870: 7 | B870: 2 | C870: 1 | D870: 1 | E870: 7211 | F870: Port Copper Concentrate Thickening | G870: - | H870: - | I870: - | J870: -
A871: 7 | B871: 2 | C871: 1 | D871: 2 | E871: 7212 | F871: Port Concentrate Filtration | G871: - | H871: - | I871: - | J871: -
A872: 7 | B872: 2 | C872: 1 | D872: 3 | E872: 7213 | F872: Port Concentrate Conveyor & Handling | G872: - | H872: - | I872: - | J872: -
A873: 7 | B873: 2 | C873: 1 | D873: 4 | E873: 7214 | F873: Port Concentrate Stacking Conveyor | G873: - | H873: - | I873: - | J873: -
A874: 7 | B874: 2 | C874: 1 | D874: 5 | E874: 7215 | F874: Port Concentrate Storage | G874: - | H874: - | I874: - | J874: -
A875: 7 | B875: 2 | C875: 1 | D875: 6 | E875: 7216 | F875: Port Concentrate Emergencg Dump Pond | G875: - | H875: - | I875: - | J875: -
A876: 7 | B876: 2 | C876: 1 | D876: 7 | E876: 7217 | F876: Process Water Treatment | G876: - | H876: - | I876: - | J876: -
A877: 7 | B877: 2 | C877: 1 | D877: 8 | E877: 7218 | F877: Sampling Plant | G877: - | H877: - | I877: - | J877: -
A878: 7 | B878: 2 | C878: 1 | D878: 9 | E878: 7219 | F878: Utilities & Services | G878: - | H878: - | I878: - | J878: -
A879: 7 | B879: 2 | C879: 2 | D879: 0 | E879: 7220 | F879: Port Site Utilities & Services | G879: - | H879: - | I879: - | J879: -
... A990: 7 | B990: 3 | C990: 9 | D990: 7 | E990: 7397 | F990: PIBT Port Generator | G990: - | H990: - | I990: - | J990: -
A991: 7 | B991: 4 | C991: 0 | D991: 0 | E991: 7400 | F991: Off-Site Rail Facilities
A992: 7 | B992: 4 | C992: 1 | D992: 0 | E992: 7410 | F992: Earthworks & Drainage
A993: 7 | B993: 4 | C993: 1 | D993: 1 | E993: 7411 | F993: Bulk Site Earthworks
A994: 7 | B994: 4 | C994: 1 | D994: 3 | E994: 7413 | F994: Site Drainage & Culverts
A995: 7 | B995: 4 | C995: 1 | D995: 4 | E995: 7414 | F995: In-Plant Roads
A996: 7 | B996: 4 | C996: 1 | D996: 5 | E996: 7415 | F996: Carparks & Hardstand Areas
A997: 7 | B997: 4 | C997: 1 | D997: 6 | E997: 7416 | F997: Site and Soil Improvements
A998: 7 | B998: 4 | C998: 1 | D998: 7 | E998: 7417 | F998: Site Security Fencing
A999: 7 | B999: 4 | C999: 1 | D999: 8 | E999: 7418 | F999: Underground Services
A1000: 7 | B1000: 4 | C1000: 2 | D1000: 0 | E1000: 7420 | F1000: Site Utilities and Services
A1001: 7 | B1001: 4 | C1001: 2 | D1001: 1 | E1001: 7421 | F1001: Stormwater Piping
A1002: 7 | B1002: 4 | C1002: 2 | D1002: 2 | E1002: 7422 | F1002: Fire Water Storage
... A1071: 8 | B1071: 1 | C1071: 0 | D1071: 0 | E1071: 8100 | F1071: Project Costs
A1072: 8 | B1072: 1 | C1072: 1 | D1072: 1 | E1072: 8111 | F1072: Project Management | G1072: - | H1072: - | I1072: - | J1072: -
A1073: 8 | B1073: 1 | C1073: 1 | D1073: 2 | E1073: 8112 | F1073: Project Controls
A1074: 8 | B1074: 1 | C1074: 1 | D1074: 3 | E1074: 8113 | F1074: Engineering and Procurement
A1075: 8 | B1075: 1 | C1075: 1 | D1075: 4 | E1075: 8114 | F1075: Construction Management
A1076: 8 | B1076: 1 | C1076: 1 | D1076: 5 | E1076: 8115 | F1076: Legal and Permitting
A1077: 8 | B1077: 1 | C1077: 1 | D1077: 6 | E1077: 8116 | F1077: Public Relations
A1078: 8 | B1078: 1 | C1078: 1 | D1078: 8 | E1078: 8118 | F1078: Community Engagement
A1079: 8 | B1079: 1 | C1079: 1 | D1079: 9 | E1079: 8119 | F1079: General and Administration
A1080: 8 | B1080: 1 | C1080: 2 | D1080: 0 | E1080: 8120 | F1080: Spares and Inventory | G1080: RDMC | H1080: RDMC | I1080: RDMC | J1080: RDMC
A1081: 8 | B1081: 1 | C1081: 2 | D1081: 1 | E1081: 8121 | F1081: Spares
A1082: 8 | B1082: 1 | C1082: 2 | D1082: 2 | E1082: 8122 | F1082: First Fills
A1083: 8 | B1083: 1 | C1083: 3 | D1083: 0 | E1083: 8130 | F1083: Pre-Production Operations
A1084: 8 | B1084: 1 | C1084: 3 | D1084: 1 | E1084: 8131 | F1084: Recruitment and Training of Operation and Maintenance Staff
A1085: 8 | B1085: 1 | C1085: 3 | D1085: 2 | E1085: 8132 | F1085: Mobile Fleet Supporting Operations
A1086: 8 | B1086: 1 | C1086: 3 | D1086: 3 | E1086: 8133 | F1086: Wet Commissioning
A1087: 8 | B1087: 1 | C1087: 3 | D1087: 4 | E1087: 8134 | F1087: Post-Commissioning Modifications
A1088: 8 | B1088: 1 | C1088: 3 | D1088: 5 | E1088: 8135 | F1088: Ramp-Up
A1089: 8 | B1089: 1 | C1089: 3 | D1089: 6 | E1089: 8136 | F1089: Working Capital
A1090: 8 | B1090: 1 | C1090: 4 | D1090: 0 | E1090: 8140 | F1090: Studies
A1091: 8 | B1091: 1 | C1091: 5 | D1091: 0 | E1091: 8150 | F1091: Closure and Rehabilitation
A1092: 8 | B1092: 1 | C1092: 6 | D1092: 0 | E1092: 8160 | F1092: Health Security and Safety
... A1096: 8 | B1096: 1 | C1096: 6 | D1096: 4 | E1096: 8164 | F1096: Safety
A1097: 8 | B1097: 1 | C1097: 7 | D1097: 0 | E1097: 8170 | F1097: Operational Readiness | G1097: - | H1097: - | I1097: - | J1097: -
A1098: 8 | B1098: 1 | C1098: 8 | D1098: 0 | E1098: 8180 | F1098: Owner’s Management
A1099: 8 | B1099: 1 | C1099: 8 | D1099: 1 | E1099: 8181 | F1099: Team
A1100: 8 | B1100: 1 | C1100: 8 | D1100: 2 | E1100: 8182 | F1100: Nonmanual Labour Expenses
A1101: 8 | B1101: 1 | C1101: 8 | D1101: 3 | E1101: 8183 | F1101: Home Office Expenses
A1102: 8 | B1102: 1 | C1102: 8 | D1102: 4 | E1102: 8184 | F1102: Project Office Expenses
A1103: 8 | B1103: 1 | C1103: 8 | D1103: 5 | E1103: 8185 | F1103: Site Office Expenses
A1104: 8 | B1104: 8 | C1104: 1 | D1104: 0 | E1104: 8810 | F1104: Allowance (Early Works)
A1105: 8 | B1105: 9 | C1105: 0 | D1105: 0 | E1105: 8900 | F1105: Contingency and Reserve
A1106: 8 | B1106: 9 | C1106: 1 | D1106: 0 | E1106: 8910 | F1106: Cost Contingency
A1107: 8 | B1107: 9 | C1107: 2 | D1107: 0 | E1107: 8920 | F1107: Schedule Contingency
A1108: 8 | B1108: 9 | C1108: 3 | D1108: 0 | E1108: 8930 | F1108: Owner Cost Reserve
A1109: 9 | B1109: 0 | C1109: 0 | D1109: 0 | E1109: 9000 | F1109: Indirect Costs (Other Parties)
A1110: 9 | B1110: 1 | C1110: 0 | D1110: 0 | E1110: 9100 | F1110: Indirect Costs (Implementation Contractors, EPCM)
A1111: 9 | B1111: 1 | C1111: 1 | D1111: 0 | E1111: 9110 | F1111: EPCM Cost | G1111: - | H1111: - | I1111: - | J1111: -
A1112: 9 | B1112: 1 | C1112: 1 | D1112: 1 | E1112: 9111 | F1112: EP Cost | G1112: - | H1112: - | I1112: - | J1112: -
...

Sheet Discipline Codes
A1: DISCIPLINE CODES
A4: Code | B4: Discipline/Function Identifier
A5: A | B5: Architectural | E5: Pending
A6: B | B6: Project Controls | E6: Updated
A7: C | B7: Civil/Concrete
A8: D | B8: Supply Chain
A9: E | B9: Electrical
A10: F | B10: Process
A11: G | B11: General
A12: H | B12: Health & Safety / Security
A13: I | B13: Instrumentation
A14: J | B14: Environmental / Social Impact
A15: L | B15: Human Resources
A16: M | B16: Mechanical
A17: N | B17: Mining
A18: P | B18: Piping
... A23: W | B23: Earthworks / Drainage / Fencing / Roads / Water

Sheet Document and Drawing Type
A1: Document and Drawing Types
A3: Code | B3: Document Type identifier | C3: Description
A4: GENERAL
A5: AUT | B5: Authority | C5: - Permitting - Authority Implementation Plan - Authority Approval Packages - Regulatory Compliance - Environmental Permitting Compliance Requirements | E5: AUT
A6: BLT | B6: Battery Limit | C6: - Battery Limit Table | E6: BLT
A7: BOE | B7: Basis of Estimate | E7: BOE
A8: BOS | B8: Basis of Schedule | E8: BOS
A9: BOM | B9: Bill of Material | E9: BOM
A10: CAL | B10: Calculation | E10: CAL
A11: CHR | B11: Chart | C11: Organization Chart, Department Chart | E11: CHR
A12: CON | B12: Contract | C12: Any contract documentation | E12: CON
A13: DBD | B13: Design Basis and Criteria | C13: Design Criteria of the Project | E13: DBD
A14: DBK | B14: Project Data Book | C14: - Manufacturer Data Records | E14: DBK
A15: DDR | B15: Document and Data Register | C15: Master Data and Document Register for Supplier, Sub-Contractors | E15: DDR
A16: DEM | B16: Demolition | C16: Demolition Documents | E16: DEM
A17: DST | B17: Datasheet | E17: DST
A18: DTA | B18: Data (Digital Record) | C18: Any data e.g. Survey Data | E18: DTA
A19: EQL | B19: Equipment List | C19: Specific list for equipments | E19: EQL
A20: EST | B20: Estimates | E20: EST
A21: EXE | B21: Execution | C21: Can be used for Supplier Data - if not specify on the list | E21: EXE
A22: FRM | B22: Forms | E22: FRM
A23: GDL | B23: Guideline | C23: - Guideline - Protocols | E23: GDL
A24: HAC | B24: Hazard Classification | C24: HAZOP, Hazard Analysis, Hazard identification | E24: HAC
A25: HMB | B25: Heat Material Balance | E25: HMB
A26: IDX | B26: Index | C26: Technical and Non-technical | E26: IDX
A27: INS | B27: Instructions | C27: e.g. operation instructions, installation instructions | E27: INS
A28: IOM | B28: Installation Operation and Maintenance Manual | E28: IOM
A29: ITP | B29: Inspection Test Plan | E29: ITP
A30: IWP | B30: Installation Work Package | E30: IWP
A31: LST | B31: List/Matrix | C31: Technical List: Valve List, Motor List, Instrument List, Spare Part List Non-Technical List: Distribution Matrix, Communication Matrix | E31: LST
A32: LTR | B32: Letter | E32: LTR
A33: MAN | B33: Manual | E33: MAN
A34: MDL | B34: Models | C34: - 3Models | E34: MDL
A35: MDR | B35: Master Document Register | C35: Document Register for Engineering - Documentation System Description - Document Filing Index - Transmittal Log - Gate Review Completed | E35: MDR
A36: MEM | B36: Memorandum | E36: MEM
A37: MOM | B37: Minutes of Meeting | E37: MOM
A38: MTO | B38: Material Take Off | E38: MTO
A39: NAR | B39: Narrative | C39: - Process Control Narrative - Safeguarding Narrative | E39: NAR
A40: NCR | B40: Non-Conformance Report | E40: NCR
A41: PCN | B41: Project Change Notice | E41: PCN
A42: PDR | B42: Procedure Deviation Request | E42: PDR
A43: PHL | B43: Philosophy | E43: PHL
A44: DOCUMENTS
A45: PLN | B45: Plan | C45: Used for non-technical plan i.e. Engineering Plan, Risk Plan, HSE Plan, Contract & Procurement Plan, HR plan, Project Execution Plan, Study Plan. etc. | E45: PLN
A46: PLC | B46: Policy | E46: PLC
A47: PRC | B47: Procedure | C47: Document represents the procedure as prescribed by the various departments. The practices generally relate to the way in which work is to be done within or for the department and also the approved way in which the Company deals with Contractors, and other organizations | E47: PRC
A48: PRO | B48: Procurement | C48: Any procurement documentation | E48: PRO
A49: QAD | B49: Quality Assurance Documents | C49: Any quality assurance documents. Except Quality Management Plan can use PLN | E49: QAD
A50: QRA | B50: Quantitive Risk Assessment | C50: Structured approach to measuring and analyzing risk using numerical data | E50: QRA
A51: REQ | B51: Request | C51: - Travel request - Any requests | E51: REQ
A52: RFA | B52: Recommendation for Award | E52: RFA
A53: RFI | B53: Request for Information | E53: RFI
A54: RPT | B54: Report | C54: Technical Report: Geotechnical Investigation Report, , etc. Non-technical Report: Safety Monthly report | E54: RPT
A55: SCH | B55: Schedule | E55: SCH
A56: SMP | B56: Sample | C56: - Interior Design and Furniture Sample - Finish Boards | E56: SMP
A57: SOP | B57: Standard Operating Procedure | E57: SOP
A58: SOW | B58: Scope of Work | C58: Document outlines the extent of work to be performed by others. The SOW may include functional specifications when a functional specification is not written which typically occurs when the contents of a functional specification is minimal (2 pages). | E58: SOW
A59: SPC | B59: Specification | C59: Document represents the design and performance requirements for materials, parts, plant and equipment | E59: SPC
A60: SPL | B60: Piping Specialty Item List | E60: SPL
A61: STD | B61: Standards | C61: For any standards, codes, and regulation documents, are generally controlled | E61: STD
A62: STR | B62: Strategy | E62: STR
A63: SUM | B63: Summary | E63: SUM
A64: TDM | B64: Technical Decision Memorandum | E64: TDM
A65: TDN | B65: Trends | C65: Project Controls Trends | E65: TDN
A66: TMP | B66: Templates | E66: TMP
A67: TOR | B67: Terms of Reference | E67: TOR
A68: TRP | B68: Test Report | C68: - Concrete test report - Any test report - Soil test report - Non-Destruction Examination Test Report - Any Test Report | E68: TRP
A69: TVR | B69: Turnover Dossier | E69: TVR
A70: VIS | B70: Visualisation | C70: - Drone Video | E70: VIS
A71: WLD | B71: Welding | C71: Any welding documents | E71: WLD
A72: DRAWINGS
A73: BLT | B73: Battery Limit | C73: - Battery Limit Drawings | E73: BLT
A74: CAE | B74: Cause and Effect Drawing | C74: - Cause and Effect Drawing, etc. | E74: CAE
A75: CRV | B75: Curves | E75: CRV
A76: DEM | B76: Demolition | C76: Demolition Drawings | E76: DEM
A77: DIA | B77: Diagram | C77: - Traffic Diagram - Schematic Diagram - Block Diagram | E77: DIA
A78: DID | B78: Ducting and Instrument Diagram | C78: HVAC Utility Piping Ducting and Instrumentation Diagram | E78: DID
A79: DTL | B79: Details | C79: Any drawings details | E79: DTL
A80: EHT | B80: Electrical Heat Tracing Isometric | E80: EHT
A81: ELE | B81: Elevation | C81: Any drawings elevation | E81: ELE
A82: FND | B82: Foundation Drawings | C82: Any foundation drawings | E82: FND
A83: GAD | B83: General Arrangement | C83: Any general arrangements drawings | E83: GAD
A84: ITD | B84: Instrumentation Drawing | E84: ITD
A85: ISO | B85: Isometrics | C85: Drawing provides a three-dimensional layout of the equipment and piping. | E85: ISO
A86: LAY | B86: Layout | C86: Any drawings layout | E86: LAY
A87: MSD | B87: Material Selection Diagram | E87: MSD
A88: PFD | B88: Process Flow Diagram | E88: PFD
A89: PID | B89: Piping and Instrumentation Diagram | E89: PID
A90: PLN | B90: Plan | C90: Any drawings plan | E90: PLN
A91: PPL | B91: Plot Plan | C91: Site Plot Plan | E91: PPL
A92: PSP | B92: Piping Support | C92: Drawing piping support. | E92: PSP
A93: SEC | B93: Section | C93: Any drawings section | E93: SEC
A94: SHP | B94: Shop Drawings | C94: Supplier Shop Drawings - Fabrication Drawings - Fabrication Steel Drawings - Erection Drawings - Plate Schedule - Spool Drawings - etc. | E94: SHP
A95: SKT | B95: Sketch | C95: Any drawings sketch | E95: SKT
A96: SLD | B96: Single Line Diagram | C96: Drawing provides a representation of an electrical system. | E96: SLD
A97: SSD | B97: Structural Steel Drawings | C97: Engineering (Design) | E97: SSD
A98: STD | B98: Standard Drawings | C98: Drawing shows the materials, set out standard construction details and provide general design data. | E98: STD
A99: TIE | B99: Tie-In | E99: TIE
